Workbook

Sheet dashboard
A1: 💄 SOCIOLLA FRAGRANCE MARKET
A5: Product, brand & customer review overview
A7: OVERVIEW
B9: =COUNTA(products!A:A) -> 475 | F9: =COUNTA(brands!A:A) -> 55 | J9: =COUNTA(reviews!A:A) -> 30491 | N9: =MEDIAN(productmetrics!D:D) -> 229000 | R9: =COUNTIF(productmetrics!E2:E1000,">=4,5")/COUNT(productmetrics!A2:A1000) -> 0.65611814
B13: PRODUCTS | F13: BRANDS | J13: REVIEWS | N13: MEDIAN PRICE | R13: ≥4.5 RATING
B17: TOP 10 BRANDS | I17: RATING DISTRIBUTION | P17: PRODUCT PERFORMANCE
E38: TOP 10 PRODUCTS | L38: BRAND PERFORMANCE

Sheet metrics
A1: overview | C1: total brands | D1: =COUNTA(brands!A:A) -> 55
C2: total products | D2: =COUNTA(products!A:A) -> 475
C3: total reviews | D3: =COUNTA(reviews!A:A) -> 30491
C4: % products with reviews | D4: =IFERROR(__xludf.DUMMYFUNCTION("COUNTUNIQUE(FILTER(reviews!B2:B997,reviews!B2:B997<>""""))/COUNTUNIQUE(FILTER(products!A2:A997,products!A2:A997<>""""))"),0.7848101265822784) -> 0.78481013

Sheet productmetrics
A1: product_id | B1: product_name | C1: brand_id | D1: price | E1: avg_rating | F1: description | G1: review_count | H1: brand_name
A2: 110247 | B2: HMNS x Tsana Fragrance Mist - Elea | C2: 62c7f51270c7e2af7c6ad720 | D2: 185000 | E2: 4.743803 | F2: <p>Pertama kali kamu bertemu Elea nanti, tutup mata kamu. Kamu akan dengan mudah mengenalinya dari rambut panjangnya, dan wangi bunga magnolianya. Yang cantik &amp; terasa hijau seperti magnolia yang baru saja dipetik.<br>Sebentar setelah kamu di dekatnya, kamu sadar kalau Elea lebih kompleks dari setangkai bunga magnolia. Elea seperti puluhan kombinasi bunga putih yang terikat dengan madu dan minyak biji ambrette. Dia terasa dekat, terasa hangat.<br>Dan untuk sesaat dalam waktu yang panjang, kamu sadar kalau akhirnya..<br>Kamu gak sendirian.<br>[Product Detail]<br>Type: Eau de Toilette<br>Group: White Floral<br>Size: 250 ml<br>Longevity: 2 - 3 hours<br>Sillage: Medium<br>Projection: 1 - 2.5 meters</p> | G2: 939 | H2: HMNS
A3: 117020 | B3: IRAI LEIMA - Extrait de Parfum | C3: 60d4e2c6443396b9504d4beb | D3: 349000 | E3: 4.8344444 | F3: <p>Parfum aquatic yang membawa sensasi udara laut segar, air yang tenang, dan drydown hangat yang terasa lembut di kulit.</p><br /><p>NOTES<br>TOP: Cassis Buds, Dalanghita, Pink Pepper<br>MID: Duchesse de Nemours, Water Iris, Raat ki Rani<br>BASE: Warm Musky Notes</p><br /><p>Cocok buat kamu yang suka parfum aquatic floral yang fresh dan soft!</p><br /><p>- Long-Lasting Scent, tahan lama untuk menemani aktivitasmu<br>- Perfect for Daily Wear, wangi yang pas dan nyaman untuk aktivitas sehari-hari</p><br /><p>Cara Pakai<br>- Semprot pada titik nadi dengan jarak 15-20 cm<br>- Tunggu hingga kering</p> | G3: 541 | H3: SAFF & Co
A4: 98385 | B4: S.O.T.B - Extrait de Parfum | C4: 60d4e2c6443396b9504d4beb | D4: 349000 | E4: 4.857915 | F4: <p>Parfum yang menangkap summer dream: kulit yang sun-kissed, beach breeze, dan suasana tropical yang fun sepanjang hari.</p><br /><p>NOTES<br>TOP: Mandarin<br>MID: Sweet Floral Notes<br>BASE: Vanilla Musk</p><br /><p>Cocok buat kamu yang suka parfum tropical floral yang fresh dan creamy!</p><br /><p>- Long-Lasting Scent, tahan lama untuk menemani aktivitasmu<br>- Perfect for Daily Wear, wangi yang pas dan nyaman untuk aktivitas sehari-hari</p><br /><p>Cara Pakai<br>- Semprot pada titik nadi dengan jarak 15-20 cm<br>- Tunggu hingga kering</p> | G4: 1158 | H4: SAFF & Co
A5: 118066 | B5: Velvet Rouge Extrait De Parfum | C5: 5db51d092023815654e4cc93 | D5: 75000 | E5: 4.8662485 | F5: <p>Scarlett Whitening Eau De Parfum 30ml<br>Scarlett Whitening Eau De Parfum a Perfection untuk berikan kesegaran dan keharuman mewah dalam setiap semprotan dengan kemasan yang Ready To Go cocok untuk temani harimu, mudah dibawa kemana pun dan kapan pun tanpa takut pecah! dengan wangi yang mewah<br>Luxurious Scent with Affordable Price.</p> | G5: 235 | H5: Scarlett Whitening
A6: 124504 | B6: Cotton Hug Extrait De Parfum | C6: 5db51d092023815654e4cc93 | D6: 67500 | E6: 4.8509666 | F6: <p>Jenis Aroma : Woody Powdery <br><br>Cotton Hug menggambarkan sosok yang tenang, lembut, dan elegan tanpa usaha berlebihan. Aroma bersih dari aldehyde, orange, dan sentuhan coconut membuka kesan fresh yang menenangkan, seperti pakaian hangat yang baru dijemur di bawah matahari pagi. Di tengahnya, perpaduan muguet, violet, dan orchid menghadirkan keanggunan feminin yang lembut. Lapisan akhir moss, sandalwood, musk, dan amber memberi sentuhan hangat dan powdery, membungkus lembut seperti pelukan penuh ketenangan. <br><br>Top Notes : Aldehyde, Ylang Ylang, Orange, Coconut, Berries <br>Heart Notes : Muguet, Rose, Orange Flower, Violet, Orchid <br>Bottom Notes : Moss, Sandalwood, Musk, Amber, Tonka</p> | G6: 92 | H6: Scarlett Whitening
A7: 113698 | B7: Cloud Mist - Annabel Lee | C7: 60d4e2c6443396b9504d4beb | D7: 199000 | E7: 4.7735507 | F7: <p>Annabel Lee menangkap nostalgia pertemuan awal, menggemakan keindahan mentah dan keajaiban tak terucapkan dari hati muda yang terjalin dalam kepolosan cinta pertama. Dari luapan emosi yang memusingkan hingga kepedihan kenaifan yang manis, syair-syair ini membisikkan kisah dramatis tentang awal yang lembut dan penemuan yang menggetarkan hati.</p><p></p><p>CHARACTER : Floral, Fruity, Gourmand</p><p>Top Notes | Iced lychee tea, Pear, Petalia</p><p>Middle Notes | Akigalawood, Roseraie de l'Hay, Cashmeran </p><p>Dry-down Notes | Crème de framboise, Amber "</p> | G7: 657 | H7: SAFF & Co
A8: 107813 | B8: Xocolatl - Extrait De Parfum | C8: 60d4e2c6443396b9504d4beb | D8: 349000 | E8: 4.8445251 | F8: <p>Parfum gourmand yang terinspirasi dari hot chocolate pertama, dipadukan mandarin manis dan heliotrope creamy yang playful.</p><br /><p>NOTES<br>TOP: Sweet Mandarin<br>MID: Heliotrope<br>BASE: Creamy Gourmand Notes</p><br /><p>Cocok buat kamu yang suka parfum chocolate gourmand yang sweet dan creamy!</p><br /><p>- Long-Lasting Scent, tahan lama untuk menemani aktivitasmu<br>- Perfect for Daily Wear, wangi yang pas dan nyaman untuk aktivitas sehari-hari</p><br /><p>Cara Pakai<br>- Semprot pada titik nadi dengan jarak 15-20 cm<br>- Tunggu hingga kering</p> | G8: 495 | H8: SAFF & Co
A9: 101486 | B9: Body Mist - Crème Canele | C9: 62bbfd4abd4201d78fc0e8f5 | D9: 34000 | E9: 4.6795062 | F9: <p>Crème Canele menghadirkan aroma vanilla yang manis dan addictive, berpadu dengan karakter cheerful, indulging, dan sensual modern.</p> <p>NOTES<br>TOP: Orange Blossom, Pear, Pink Pepper<br>MID: Jasmine, Rose, Freesia<br>BASE: Vanilla, Patchouli, Cedar, Musk</p> <p>Cocok buat kamu yang suka parfum warm vanilla yang sweet, spicy, dan gourmand!</p> <p>- Long-Lasting Scent, tahan lama untuk menemani aktivitasmu<br>- Perfect for Daily Wear, wangi yang pas dan nyaman untuk aktivitas sehari-hari</p> <p>Cara Pakai<br>- Semprot pada titik nadi dengan jarak 15-20 cm<br>- Tunggu hingga kering</p> | G9: 619 | H9: Bonavie
A10: 124503 | B10: Sweetie Love Extrait De Parfum | C10: 5db51d092023815654e4cc93 | D10: 67500 | E10: 4.9111111 | F10: <p>Jenis Aroma : Fruity Floral<br><br>Sweetie Love memancarkan kepribadian yang ceria, youthful, dan penuh cinta. Dibuka dengan aroma manis caramel, segarnya apple dan green pear, menghadirkan kesan playful sejak semprotan pertama. Di tengahnya, perpaduan magnolia, rose, dan sedikit licorice memberi sentuhan feminin yang lembut dan memikat. Ditutup dengan musk dan amber yang hangat, meninggalkan jejak manis yang romantis dan bertahan lama, semanis momen jatuh cinta pertama kali.<br><br>Top Notes : Caramel, Apple, Green Pear<br>Heart Notes : Licorice, Magnolia, Rose<br>Bottom Notes : Musk, Amber</p> | G10: 64 | H10: Scarlett Whitening
A11: 109448 | B11: Scarlett Eau De Parfume Sweet Memories | C11: 5db51d092023815654e4cc93 | D11: 75000 | E11: 4.8341443 | F11: <p>Scarlett Parfume Sweet Memories EDP 30 ml<br>Scarlett Whitening Eau De Parfum Sweet Memories Untuk berikan kesegaran dan keharuman mewah dalam setiap semprotan dengan kemasan yang Ready To Go cocok untuk temani harimu, mudah dibawa kemana pun dan kapan pun tanpa takut pecah! dengan wangi Amber Fougere yang menjadikan parfum ini mempunyai wangi yang mewah.<br><br>Luxurious Scent with Affordable Price.<br>Gender - Unisex | Woman<br>Top Notes - Egyptian Balsam, Grapefruit, Damask Rose<br>Middle Notes - Vanilla, Honeysuckle, Jasmine, Peach<br>Base Notes - Musky, Cashmeran, Amber</p> | G11: 163 | H11: Scarlett Whitening
A12: 109449 | B12: Scarlett Eau De Parfume Dreamy | C12: 5db51d092023815654e4cc93 | D12: 75000 | E12: 4.8687235 | F12: <p>Scarlett Parfume Dreamy EDP 30 ml<br>Scarlett Whitening Eau De Parfum Dreamy Untuk berikan kesegaran dan keharuman mewah dalam setiap semprotan dengan kemasan yang Ready To Go cocok untuk temani harimu, mudah dibawa kemana pun dan kapan pun tanpa takut pecah! dengan wangi floral white Floral Ambery yang menjadikan parfum ini mempunyai wangi yang mewah.<br><br>Luxurious Scent with Affordable Price.<br>Gender - Unisex | Woman<br>Top Notes - Bergamot, Mandarin, Ginger, Pear<br>Middle Notes - Jasmine, Tuberose, Orange Flower, Gourmand<br>Base Notes - Amber Dry, Cashmeran, Heliotrope, Vanilla</p> | G12: 182 | H12: Scarlett Whitening
A13: 114830 | B13: Mykonos Satin Blanc | C13: 66fba216e8005543698af0d8 | D13: 379000 | E13: 4.8845093 | F13: <p>Parfum yang menghadirkan kesan clean dan modern lewat fresh woody aromatic notes yang elegan.</p> <p>NOTES<br>TOP: Bergamot, Black Pepper, Green Apple<br>MIDDLE: Cedar Wood, Jasmine Tea, Floral Bouquet, Aquatic Notes<br>BASE: White Amber, Tonka Bean, Vanilla</p> <p>Cocok buat kamu yang suka parfum fresh dan elegant!</p> <p>- Long-Lasting Scent, tahan lama untuk menemani aktivitasmu<br>- Perfect for Daily Wear, wangi yang pas dan nyaman untuk aktivitas sehari-hari</p> <p>Cara Pakai<br>- Semprot pada titik nadi dengan jarak 15-20 cm<br>- Tunggu hingga kering</p> | G13: 206 | H13: Mykonos
... A300: 117726 | B300: CARESO Eau De Toilette Honey Blush | C300: 5f5640bc311107db64724988 | D300: 82000 | E300: 4.7272727 | F300: <p><em>Honey varies in smell depending on the environment and which flowers the bees pollinated to produce nectar. Every spray is delicate and gives an interesting combination that truly enhance the senses.<br>The perfume will last upto 6 hours.</em></p> | G300: 23 | H300: Careso
A301: 125426 | B301: IN THE MOOD FOR x IGNIO Bundle Set [Crush & Eclipse] | C301: 667d3cc467565050b7424bc9 | D301: 248000 | E301: 0 | G301: 0 | H301: In The Mood For
A302: 120630 | B302: MERCREDI LAIT EDP | C302: 654070018fac4010da648abf | D302: 158000 | E302: 0 | F302: <p>Parfum fruity yang ringan, juicy, dan manis seperti permen melon dalam udara sejuk.</p> <p>NOTES: Melon Candy, Cool Air Accord, dan Soft Sweet Notes.</p> <p>Cocok buat kamu yang menyukai aroma buah manis yang cheerful, ringan, dan mudah dipakai.</p> <p>- Juicy Melon Scent, aroma melon terasa segar dan menyenangkan<br>- Cooling Impression, nuansa udara sejuk membuat aroma tidak terasa berat<br>- Soft Sweet Trail, manisnya lembut namun tetap addictive<br>- Long-Lasting Scent, tahan lama untuk menemani aktivitasmu</p> <p>Cara Pakai:<br>- Semprotkan secukupnya ke titik nadi dari jarak 10–20 cm</p> | G302: 0 | H302: Mercredi
A303: 114831 | B303: Mykonos Sparkling Rose | C303: 66fba216e8005543698af0d8 | D303: 99000 | E303: 4 | F303: <p>Parfum yang menghadirkan kilau rose yang romantis dengan sentuhan red berries, plum, dan warm woody notes.</p> <p>NOTES<br>TOP: Damask Rose, Orange, Geranium<br>MIDDLE: May Rose, Sparkling Red Berries, Plum, Sandalwood<br>BASE: Patchouli, Amber, Guaiac Wood, Musk</p> <p>Cocok buat kamu yang suka parfum rose floral, fruity, dan elegant!</p> <p>- Long-Lasting Scent, tahan lama untuk menemani aktivitasmu<br>- Perfect for Daily Wear, wangi yang pas dan nyaman untuk aktivitas sehari-hari</p> <p>Cara Pakai<br>- Semprot pada titik nadi dengan jarak 15-20 cm<br>- Tunggu hingga kering</p> | G303: 2 | H303: Mykonos
A304: 123468 | B304: Rose Moss Extrait de Parfum | C304: 62fb16f36d42e66ec212086f | D304: 329000 | E304: 0 | F304: <p>Parfum yang menggambarkan mawar dari taman rahasia setelah hujan, floral, green, dan penuh misteri.</p> <p>NOTES<br>TOP: Blackcurrant, Cardamom, Chamomile, Lavandin<br>MID: Rose, Jasmine, Neroli, Petitgrain, Geranium, Clove<br>BASE: Moss, Benzoin, Fir</p> <p>Cocok buat kamu yang suka parfum rose green yang earthy dan elegant!</p> <p>- Long-Lasting Scent, tahan lama untuk menemani aktivitasmu<br>- Perfect for Daily Wear, nyaman dipakai untuk aktivitas sehari-hari</p> <p>Cara Pakai<br>- Semprot pada titik nadi dengan jarak 15-20 cm<br>- Tunggu hingga kering</p> | G304: 0 | H304: Verites
A305: 114843 | B305: Mykonos Hawaiian Crush | C305: 66fba216e8005543698af0d8 | D305: 99000 | E305: 4.4398148 | F305: <p>Parfum yang menghadirkan sensasi fruity tea floral dengan sentuhan lychee, black tea, dan warm musky notes.</p> <p>NOTES<br>TOP: Lychee, Red Fruits, Black Tea<br>MIDDLE: Rose, Lily of the Valley, Lychee, Black Tea<br>BASE: Amber, Patchouli, Musk, Incense</p> <p>Cocok buat kamu yang suka parfum fruity dan elegant!</p> <p>- Long-Lasting Scent, tahan lama untuk menemani aktivitasmu<br>- Perfect for Daily Wear, wangi yang pas dan nyaman untuk aktivitas sehari-hari</p> <p>Cara Pakai<br>- Semprot pada titik nadi dengan jarak 15-20 cm<br>- Tunggu hingga kering</p> | G305: 9 | H305: Mykonos
A306: 114797 | B306: Mykonos Paradise EDP | C306: 66fba216e8005543698af0d8 | D306: 179000 | E306: 4.6666667 | F306: <p>Parfum yang menghadirkan suasana paradise yang cerah lewat coconut, fruity notes, dan sentuhan floral tropis.</p> <p>NOTES<br>TOP: Coconut, Mandarin Orange, Pear, Pineapple<br>MIDDLE: Frangipani, Jasmine, Lily<br>BASE: Amber, Vanilla, Woody Notes</p> <p>Cocok buat kamu yang suka parfum tropical, creamy, dan fruity floral!</p> <p>- Long-Lasting Scent, tahan lama untuk menemani aktivitasmu<br>- Perfect for Daily Wear, wangi yang pas dan nyaman untuk aktivitas sehari-hari</p> <p>Cara Pakai<br>- Semprot pada titik nadi dengan jarak 15-20 cm<br>- Tunggu hingga kering</p> | G306: 3 | H306: Mykonos
A307: 111794 | B307: Sunset Hour | C307: 662b56b473a9ec785fc0b744 | D307: 249000 | E307: 5 | F307: <p>Parfum yang menangkap momen golden hour lewat aroma orange, vanilla, dan musk yang manis dan comforting.</p><br /><p>NOTES<br>TOP: Bergamot, Orange, Sugar<br>MIDDLE: Vanilla, Licorice, Violet Blossoms<br>BASE: Sandalwood, Musk, Star Anise </p> <p>Cocok buat kamu yang suka parfum sweet, warm, dan intoxicating!</p> <p>- Long-Lasting Scent, tahan hingga 8 jam<br>- Perfect for Daily Wear, wangi yang pas dan nyaman untuk aktivitas sehari-hari</p> <p>Cara Pakai<br>- Semprot pada titik nadi dengan jarak 15-20 cm<br>- Tunggu hingga kering</p> | G307: 1 | H307: YN Perfumery
A308: 106058 | B308: Perfume Mist Lily & Suede | C308: 63f33afa031c4c49121df81c | D308: 95000 | E308: 4.382716 | F308: <p>Lily &amp; Suede menghadirkan pesona feminin yang lembut dan romantis, terinspirasi dari cinta pertama yang murni.</p><br /><p>NOTES<br>TOP: Lily of the Valley<br>MID: Amber<br>BASE: Apple Zest</p> <p>Cocok buat kamu yang suka parfum floral feminine yang soft, romantic, dan charming!</p> <p>- Long-Lasting Scent, tahan lama untuk menemani aktivitasmu<br>- Perfect for Daily Wear, wangi yang pas dan nyaman untuk aktivitas sehari-hari</p> <p>Cara Pakai<br>- Semprot pada titik nadi dengan jarak 15-20 cm<br>- Tunggu hingga kering</p> | G308: 27 | H308: Elmer
A309: 117716 | B309: CARESO Eau De Toilette Spring In New York | C309: 5f5640bc311107db64724988 | D309: 82000 | E309: 4.3333333 | F309: <p><em>The essence of spring! The freshness of ripe Pears combine with the newly bloomed Freesias, balanced by Roses, Ambers, Patchouli and Whitemusk.<br>The perfume will last upto 6 hours.</em></p> | G309: 6 | H309: Careso
A310: 106268 | B310: Scent of Jarte Blank Space Eau De Parfum | C310: 5d3ac2ffa6992471b7c971d6 | D310: 275000 | E310: 4.5757576 | F310: <p>Blank Space membawa nuansa delicacy yang fresh dan sweet, dengan kesan feminin yang membuat aroma terasa memorable.</p><br /><p>NOTES<br>TOP: Mandarin, Blackcurrant, Orange Blossom<br>MID: Pear, Tuberose, Jasmine<br>BASE: Musk, Cedarwood, Vanilla</p><br /><p>Cocok buat kamu yang suka parfum fresh, sweet, feminine, dan elegant!</p> <p>- Long-Lasting Scent, tahan hingga 6–8 jam<br>- Perfect for Daily Wear, wangi yang pas dan nyaman untuk aktivitas sehari-hari</p> <p>Cara Pakai<br>- Semprot pada titik nadi dengan jarak 15-20 cm<br>- Tunggu hingga kering</p> | G310: 11 | H310: Jarte Beauty
A311: 120631 | B311: MERCREDI SOIA EDP | C311: 654070018fac4010da648abf | D311: 158000 | E311: 0 | F311: <p>Parfum creamy dan hangat yang terasa lembut seperti pagi santai dengan pakaian ternyaman.</p> <p>NOTES: Creamy Accord, Nutty Notes, Earthy Notes, dan Soft Musk.</p> <p>Cocok buat kamu yang menyukai aroma creamy, nutty, earthy, dan comforting.</p> <p>- Creamy Warm Scent, aroma lembut memberi kesan cozy<br>- Nutty-Earthy Character, perpaduan nutty dan earthy terasa unik serta menenangkan<br>- Soft Skin-Like Trail, jejak aromanya lembut dan dekat dengan kulit<br>- Long-Lasting Scent, tahan lama untuk menemani aktivitasmu</p> <p>Cara Pakai:<br>- Semprotkan secukupnya ke titik nadi dari jarak 10–20 cm</p> | G311: 0 | H311: Mercredi
A312: 124844 | B312: On A Date Eau De Parfum | C312: 62fb16f36d42e66ec212086f | D312: 239000 | E312: 4.5 | F312: <p>Parfum yang dibuat untuk meninggalkan kesan manis, elegan, dan memorable seperti malam yang sempurna.</p> <p>NOTES<br>TOP: Strawberry, Blackcurrant, Lychee, Mint<br>MID: Cinnamon, Orange Blossom, Rose<br>BASE: Edible Notes, Dry Woods, Smoky Notes</p> <p>Cocok buat kamu yang suka parfum fruity rose yang sweet dan memorable!</p> <p>- Long-Lasting Scent, tahan lama untuk menemani aktivitasmu<br>- Perfect for Daily Wear, nyaman dipakai untuk aktivitas sehari-hari</p> <p>Cara Pakai<br>- Semprot pada titik nadi dengan jarak 15-20 cm<br>- Tunggu hingga kering</p> | G312: 2 | H312: Verites
A313: 125974 | B313: Out West - A.M | C313: 630c79bfa09d276df7478c18 | D313: 579000 | E313: 4 | F313: <p>Parfum yang dirancang untuk merekah dalam cahaya pagi, dengan pink pepper, lemon, jahe, resin hangat, dan leather yang berlapis.</p> <p>NOTES<br>TOP: Pink Pepper CO₂ LMR, Lemon Oil Spain LMR, Jahe<br>MIDDLE: Cypriol, Balsamic<br>BASE: Cedarwood, Patchouli Oil Indonesia LMR, Nuansa Leather</p> <p>Cocok buat kamu yang suka parfum woody dan leathery!</p> <p>- Long-Lasting Scent, tahan lama untuk menemani aktivitasmu<br>- Perfect for Daily Wear, wangi yang pas dan nyaman untuk aktivitas sehari-hari</p> <p>Cara Pakai<br>- Semprot pada titik nadi dengan jarak 15-20 cm<br>- Tunggu hingga kering</p> | G313: 1 | H313: Alchemist Fragrance
... A350: 125402 | B350: IN THE MOOD FOR x IGNIO Bundle Set [Date & Eclipse] | C350: 667d3cc467565050b7424bc9 | D350: 248000 | E350: 0 | F350: <p><strong>His &amp; Hers<br>Couple Bundles </strong><br><br><strong>IN THE MOOD FOR - DATE:<br></strong>Aroma mewah dari Eropa yang membawamu pada memori kencan pertama yang manis dan romantis.<br><br>Scent Notes: <br>Top: Rose, Peach, Apple<br>Middle: Bergamot, Tuberose, Jasmine<br>Base: Woods, Ambers, Vanilla<br><br><strong>IGNIO - Eclipse:<br></strong>Scent Notes: <strong><br></strong>Top: Juniper Berry, Lemon, Black Pepper<br>Middle: Grass, Elemi, Geranium<br>Base: Amber, Wood, Musk</p> | G350: 0 | H350: In The Mood For
A351: 125427 | B351: IN THE MOOD FOR x IGNIO Bundle Set [Crush & Flame] | C351: 667d3cc467565050b7424bc9 | D351: 248000 | E351: 0 | G351: 0 | H351: In The Mood For
A352: 123473 | B352: Oud Rages Extrait de Parfum | C352: 62fb16f36d42e66ec212086f | D352: 329000 | E352: 0 | F352: <p>Parfum yang menggambarkan sisi oud yang liar, bold, dan berani mendobrak aturan.</p> <p>NOTES<br>TOP: Nutmeg, Saffron, Lavender<br>MID: Leather, Tobacco, Oud<br>BASE: Patchouli, Moss, Musk, Oriental Woody</p> <p>Cocok buat kamu yang suka parfum oud leather yang intense dan powerful!</p> <p>- Long-Lasting Scent, tahan lama untuk menemani aktivitasmu<br>- Perfect for Daily Wear, nyaman dipakai untuk aktivitas sehari-hari</p> <p>Cara Pakai<br>- Semprot pada titik nadi dengan jarak 15-20 cm<br>- Tunggu hingga kering</p> | G352: 0 | H352: Verites
A353: 109392 | B353: Invigorating Waterfall Eau de Toilette | C353: 657ad93e28f41e975c8a966c | D353: 82900 | E353: 5 | F353: <p>Kahf Invigroating Waterfall Eau de Toilette merupakan parfum dengan paduan aroma Aquatic dan Floral yang memberikan kesegaran nuansa air terjun. Dilengkapi dengan aroma Citrus dan Aromatik membawa kita ke dalam atmosfir yang penuh semangat selayaknya air memberikan energi pada setiap kehidupan.<br>&nbsp;<br>&nbsp;Keunggulan dari item ini adalah:<br>&nbsp;1. Aroma yang memberikan kesegaran<br>&nbsp;2. Tahan hingga 12 jam<br>&nbsp;3. Aroma khas yang memberikan kesegaran alam<br>&nbsp;4. Cocok untuk pemakaian sehari-hari<br></p> | G353: 2 | H353: Kahf
A354: 108423 | B354: De Club Eau De Parfum | C354: 62fb16f36d42e66ec212086f | D354: 269000 | E354: 4.7142857 | F354: <p>Parfum yang menggambarkan malam eksklusif yang bebas, elegan, dan penuh pesona tanpa perlu banyak usaha.</p> <p>NOTES<br>TOP: Lavandin, Clary Sage<br>MID: Virginia Cedarwood<br>BASE: Vetiver</p> <p>Cocok buat kamu yang suka parfum aromatic woody yang masculine dan refined!</p> <p>- Long-Lasting Scent, tahan lama untuk menemani aktivitasmu<br>- Perfect for Daily Wear, nyaman dipakai untuk aktivitas sehari-hari</p> <p>Cara Pakai<br>- Semprot pada titik nadi dengan jarak 15-20 cm<br>- Tunggu hingga kering</p> | G354: 7 | H354: Verites
A355: 106054 | B355: Perfume Mist Pear & Freesia | C355: 63f33afa031c4c49121df81c | D355: 95000 | E355: 4.3333333 | F355: <p>Pear &amp; Freesia menghadirkan kesegaran crisp pear dalam buket freesia putih dengan sentuhan patchouli yang halus, memberi kesan elegan namun chic.</p><br /><p>NOTES<br>TOP: Crisp Pear<br>MID: Freesia<br>BASE: Patchouli</p> <p>Cocok buat kamu yang suka parfum fruity floral yang fresh, elegant, dan effortless!</p> <p>- Long-Lasting Scent, tahan lama untuk menemani aktivitasmu<br>- Perfect for Daily Wear, wangi yang pas dan nyaman untuk aktivitas sehari-hari</p> <p>Cara Pakai<br>- Semprot pada titik nadi dengan jarak 15-20 cm<br>- Tunggu hingga kering</p> | G355: 13 | H355: Elmer
A356: 124830 | B356: Honey Bee Gentle Mist | C356: 62fb16f36d42e66ec212086f | D356: 209000 | E356: 5 | F356: <p>Floral, Fruity<br>Top : Mandarin, Raspberry, Pear<br>Mid : Jasmine, Gardenia, Orange Blossom<br>Dry : Patchouli, Amber, White Honey<br><br>“Honey Bee” menangkap suasana taman yang disinari matahari, penuh bunga bermekaran dan udara manis yang hangat. Dibuka dengan mandarin, raspberry, dan pear yang juicy dan cerah. Di bagian tengah, jasmine, gardenia, dan orange blossom membentuk bouquet floral yang lush dan hidup.<br><br>Di akhir, patchouli, amber, dan white honey menjadi bintang utama—memberikan sentuhan manis, creamy, dan hangat yang memeluk kulit dengan lembut. “Honey Bee” cocok untuk kamu yang mencintai aroma floral manis alami dan ingin terasa hangat sepanjang hari.</p> | G356: 1 | H356: Verites
A357: 124827 | B357: Cake Me Away Gentle Mist | C357: 62fb16f36d42e66ec212086f | D357: 209000 | E357: 0 | F357: <p>Top : Pear, Berry, Peach, Mandarin<br>Mid : Jasmine/ White Floral, Lily of the Valley<br>Dry : Vanilla, Amber, Musk<br><br>“Cake Me Away” adalah wewangian manis dan lezat yang menangkap kesenangan menikmati dessert favoritmu. Aromanya dibuka dengan perpaduan buah yang juicy—pear, berry, peach, dan mandarin—memberikan kesan cerah dan menggugah selera, seperti gigitan pertama kue dengan frosting sempurna.<br><br>Di bagian tengah, hadir sentuhan floral lembut dari jasmine dan lily of the valley yang menyeimbangkan rasa manisnya. Penutupnya hangat dan menenangkan, dengan vanilla creamy, amber yang rich, dan musk lembut yang membalut kulit dengan aroma manis yang cozy dan tahan lama.<br><br>“Cake Me Away” pas untuk kamu yang suka menikmati momen-momen manis dan ingin wewangian yang terasa senyaman sepotong kue.</p> | G357: 1 | H357: Verites
A358: 111816 | B358: Chillin Baby | C358: 655dc43d5d8272b99f510b3b | D358: 129000 | E358: 4 | F358: <p>Parfum yang menghadirkan vibes rich baby dengan aroma floral sweet dan musky ambery yang bikin mood naik lagi.</p> <p>NOTES<br>TOP: Peach, Apple, Melon<br>MIDDLE: Mimosa, Tuberose, Freesia, Jasmine, Ylang-Ylang<br>BASE: Sandalwood, Musk, Oakmoss </p> <p>Cocok buat kamu yang suka parfum floral fruity!</p> <p>- Long-Lasting Scent, tahan lama untuk menemani aktivitasmu<br>- Perfect for Daily Wear, wangi yang pas dan nyaman untuk aktivitas sehari-hari</p> <p>Cara Pakai<br>- Semprot pada titik nadi dengan jarak 15-20 cm<br>- Tunggu hingga kering</p> | G358: 3 | H358: Onix
A359: 109395 | B359: Revered Oud Eau de Toilette | C359: 657ad93e28f41e975c8a966c | D359: 82900 | E359: 4.5555556 | F359: <p>Kahf Revered Oud Eau de Toilette merupakan parfum yang menghadirkan aroma Oud dan Amber yang lekat dengan warisan tradisi budaya. Hint Gourmand dan Vanilla membawa kembali manisnya memori terdahulu. Sentuhan awal Rose membuat kita semakin cinta pada tempat kita bermula.<br>&nbsp;<br>&nbsp;Keunggulan dari item ini adalah:<br>&nbsp;1. Aroma yang memberikan kesan kasual<br>&nbsp;2. Tahan hingga 12 jam<br>&nbsp;3. Aroma khas yang memberikan kesegaran alam<br>&nbsp;4. Cocok untuk pemakaian sehari-hari<br></p> | G359: 3 | H359: Kahf
A360: 117775 | B360: Tahiti Sunrise | C360: 678f22b3bf9a94d16f30d103 | D360: 229000 | E360: 3.3333333 | F360: <p>Parfum fresh tropical yang menghadirkan suasana sunrise di Tahiti yang cerah dan menenangkan.</p> <p>NOTES<br>TOP: Coconut, Fruity Notes<br>MID: Sea Salt, Solar Notes<br>BASE: Vanilla, Musk, Amber</p> <p>Cocok buat kamu yang suka parfum fresh tropical dengan karakter segar, cerah, dan uplifting!</p> <p>- Long-Lasting Scent, tahan lama untuk menemani aktivitasmu<br>- Fresh Uplifting Aroma, memberikan energi positif sepanjang hari<br>- Perfect for Evening &amp; Formal Occasion, cocok dipakai saat malam hari atau acara formal</p> <p>Cara Pakai<br>- Semprot pada titik nadi dengan jarak 15-20 cm<br>- Tunggu hingga kering</p> | G360: 1 | H360: Alt perfumery
A361: 106057 | B361: Perfume Mist Oakwood & Leather | C361: 63f33afa031c4c49121df81c | D361: 95000 | E361: 4.5 | F361: <p>Oakwood &amp; Leather melambangkan karisma dengan perpaduan maskulin antara kayu dan vetiver yang memikat setiap momen menjadi kenangan abadi.</p><br /><p>NOTES<br>TOP: Oakwood, Leather<br>MID: Geranium, Vetiver<br>BASE: Tonka Bean</p> <p>Cocok buat kamu yang suka parfum woody masculine yang charismatic, warm, dan refined!</p> <p>- Long-Lasting Scent, tahan lama untuk menemani aktivitasmu<br>- Perfect for Daily Wear, wangi yang pas dan nyaman untuk aktivitas sehari-hari</p> <p>Cara Pakai<br>- Semprot pada titik nadi dengan jarak 15-20 cm<br>- Tunggu hingga kering</p> | G361: 6 | H361: Elmer
A362: 124832 | B362: Poetry & Pastry Gentle Mist | C362: 62fb16f36d42e66ec212086f | D362: 209000 | E362: 0 | F362: <p>Fruity, Floral, Musk<br>Top : Citrus peel, Milk Chocolate, Caramelized Pear Note<br>Mid : Lily of the Valley, Orange Blossom, Antillone*<br>Dry : Coconut milk, Sandalwood cream, Precious Musks<br><br>“Poetry &amp; Pastry” adalah wewangian charming yang memadukan gourmand dan floral, terinspirasi dari suasana kafe yang cozy. Dibuka dengan citrus peel yang segar, berpadu dengan milk chocolate dan caramelized pear yang manis dan menggoda.<br><br>Bagian tengah menghadirkan lily of the valley dan orange blossom yang lembut, dengan sentuhan Antillone* yang memberi karakter unik. Penutupnya creamy dan comforting, dengan coconut milk, sandalwood cream, dan soft musk yang terasa hangat dan mewah. Cocok untuk kamu yang menyukai manisnya hidup dengan sentuhan elegan.</p> | G362: 0 | H362: Verites
A363: 117433 | B363: On Cloud Nine | C363: 662b56b473a9ec785fc0b744 | D363: 279000 | E363: 0 | F363: <p><em>In collaboration with Maria Karina, YN Perfumery presents the serene, uplifting sensation of "On Cloud Nine," a fragrance that will take you to a place of calm and joy. With fresh freesia and crisp pear leading the way, the scent opens with a burst of lightness and elegance. As it settles, the warm, earthy depth of patchouli gently wraps you in a sense of comfort and tranquility. Inspired by Maria Karina’s graceful balance of life’s many roles, this fragrance encourages you to embrace peace and simplicity in every moment, leaving you feeling refreshed and empowered.<br><br>Size: 60ml<br>Longevity: 8 hours<br>Gender: Feminine<br>Character: Light, Airy, Breezy<br><br>Top : Lemon, Freesia, Rose, Blackcurrant, Pear<br>Middle : Jasmine, Anise, Sandalwood, Jasmine Sambac Absolute, Floral Accord<br>Bottom : Vanilla, Musk, Lily Of The Valley, Dry Wood, Patchouli<br><br>SUDAH TERDAFTAR BPOM NA18240606378</em></p> | G363: 0 | H363: YN Perfumery
... A393: 118644 | B393: Gourmand Series Set | C393: 5d3ac2ffa6992471b7c971d6 | D393: 855000 | E393: 0 | F393: <p>Bundle ini berisi:<br>1 pcs Jarte Beauty Mango Sticky Rice Extrait De Parfum 30ml<br>1 pcs Jarte Beauty Matcha Latte Extrait De Parfum 30ml<br>1 pcs Jarte Beauty Peppermint Tea Extrait De Parfum 30ml<br>FREE Block It Out Sunscreen 50ml<br><br>Untuk setiap pembelian produk bundle ini, Anda akan mendapatkan Block It Out Sunscreen 50ml gratis!</p> | G393: 0 | H393: Jarte Beauty
A394: 124986 | B394: IN THE MOOD FOR Bundle Set Kiss & Play | C394: 667d3cc467565050b7424bc9 | D394: 198000 | E394: 0 | G394: 0 | H394: In The Mood For
A395: 125399 | B395: IN THE MOOD FOR x IGNIO Bundle Set [Kiss & Spark] | C395: 667d3cc467565050b7424bc9 | D395: 248000 | E395: 0 | F395: <p><strong>His &amp; Hers</strong><br>Couple Bundles <br><br><strong>IN THE MOOD FOR - Kiss:<br></strong>Aroma mewah dari Eropa yang tahan lama.<br><br>Top: Fruity Pear, Ozonic Coffee<br>Mid: White Floral, Jasmine, Orange Blossom<br>Bottom: Cashmere Wood, Cedarwood, Patchouli, Vanilla<br><br><br><br><strong>IGNIO - Spark<br></strong>Scent Notes:<br>Top: Mandarin, Orange<br>Middle: Lavender, Aquatic Accord<br>Base: Patchouli, Red Cedar, Ambrox</p> | G395: 0 | H395: In The Mood For
A396: 126287 | B396: Love Spell & Crush | C396: 667d3cc467565050b7424bc9 | D396: 198000 | E396: 0 | F396: <p>Aroma mewah dari Eropa yang tahan lama.<br><br>IN THE MOOD FOR Love Spell: <br>Top: Freesia, Lemon, Nectarine Blossom, Apple<br>Mid: Marshmallow, Strawberry, Coconut, Orange Blossom<br>Bottom: Whipped Cream, Sugar, Vanilla, Musk, Raspberry, Amber<br><br>IN THE MOOD FOR Crush Scent Notes:<br>Top: Orange, Bergamot, Lemon<br>Mid: Fruity, Cedar, Sandalwood<br>Base: White Musk, Vanilla, Amber</p> | G396: 0 | H396: In The Mood For
A397: 125397 | B397: His & Her Couple Bundle Set [Play & Spark] | C397: 667d3cc467565050b7424bc9 | D397: 248000 | E397: 0 | F397: <p><strong>His &amp; Hers</strong><br>Couple Bundles <br><br><strong>IN THE MOOD FOR - Play:<br></strong>Aroma mewah dari Eropa yang menggambarkan momen bersama menjadi pengalaman yang tak terlupakan.<br><br>Scent Notes:<br>Top: Lavender, Mandarin Orange, Bergamot<br>Mid: Tunisian Orange Blossom, Jasmine Sambac, Orchids<br>Base: Madagscar Vanilla, Tonka Bean, Ambergris<br><br><strong>IGNIO - Spark<br></strong>Scent Notes:<br>Top: Mandarin, Orange<br>Middle: Lavender, Aquatic Accord<br>Base: Patchouli, Red Cedar, Ambrox</p> | G397: 0 | H397: In The Mood For
A398: 125400 | B398: IN THE MOOD FOR x IGNIO Bundle Set [Cuddle & Spark] | C398: 667d3cc467565050b7424bc9 | D398: 248000 | E398: 0 | F398: <p><strong>His &amp; Hers</strong><br>Couple Bundles <br><br><strong>IN THE MOOD FOR - Cuddle:<br></strong>Aroma mewah dari Eropa yang tahan lama. <br><br>Scent Notes:<br>Top: Aldehydes, Lily<br>Mid : Rose, Iris<br>Base : Musk, Ambrette<br><br><strong>IGNIO - Spark<br></strong>Scent Notes:<br>Top: Mandarin, Orange<br>Middle: Lavender, Aquatic Accord<br>Base: Patchouli, Red Cedar, Ambrox</p> | G398: 0 | H398: In The Mood For
A399: 125405 | B399: IN THE MOOD FOR x IGNIO Bundle Set [Kiss & Eclipse] | C399: 667d3cc467565050b7424bc9 | D399: 248000 | E399: 0 | F399: <p><strong>His &amp; Hers<br>Couple Bundles </strong><br><br><br><strong>IN THE MOOD FOR - Kiss:<br></strong>Aroma mewah dari Eropa yang tahan lama.<br><br>Top: Fruity Pear, Ozonic Coffee<br>Mid: White Floral, Jasmine, Orange Blossom<br>Bottom: Cashmere Wood, Cedarwood, Patchouli, Vanilla<br><br><br><strong>IGNIO - Eclipse:<br></strong>Scent Notes: <strong><br></strong>Top: Juniper Berry, Lemon, Black Pepper<br>Middle: Grass, Elemi, Geranium<br>Base: Amber, Wood, Musk</p> | G399: 0 | H399: In The Mood For
A400: 126278 | B400: Love Spell & Love | C400: 667d3cc467565050b7424bc9 | D400: 198000 | E400: 0 | F400: <p>Aroma mewah dari Eropa yang tahan lama.<br><br>IN THE MOOD FOR Love Spell: <br>Top: Freesia, Lemon, Nectarine Blossom, Apple<br>Mid: Marshmallow, Strawberry, Coconut, Orange Blossom<br>Bottom: Whipped Cream, Sugar, Vanilla, Musk, Raspberry, Amber<br><br>IN THE MOOD FOR Love Scent Notes:<br>Top: Pear, Apple<br>Mid: Jasmine<br>Base: Musk, Amber</p> | G400: 0 | H400: In The Mood For
A401: 125412 | B401: IN THE MOOD FOR x IGNIO Bundle Set [Cuddle & Flame] | C401: 667d3cc467565050b7424bc9 | D401: 248000 | E401: 0 | F401: <p><strong>His &amp; Hers<br>Couple Bundles </strong><br><br><strong>IN THE MOOD FOR - Cuddle:<br></strong>Aroma mewah dari Eropa yang tahan lama. <br><br>Scent Notes:<br>Top: Aldehydes, Lily<br>Mid : Rose, Iris<br>Base : Musk, Ambrette<br><br><br><strong>IGNIO - Flame:<br></strong>Scent Notes:<br>Top: Apple, Basil, Lemon, Ozone<br>Middle: Floral, Nutmeg, White Flowers<br>Base: Cedarwood, Incense, Patchouli, Vetiver</p> | G401: 0 | H401: In The Mood For
A402: 97094 | B402: Orgsm | C402: 62c7f51270c7e2af7c6ad720 | D402: 323000 | E402: 4.7099846 | F402: <p>HMNS “O” is our very first feminine perfume with a power of making you irresistible with a scent that generates insatiable thirst. Inspired by worlds’ most bestselling notes for women, HMNS “O” perfume will be released for worldwide, So don’t miss your chance &lt;3. </p><p>Merupakan formulasi pertama dari Series Gen – XX, HMNS “O” hadir dengan top notes red apple, middle notes florals dari Rose, Jasmine, Peony yang memberikan kesan rich, luxury, &amp; romantic. Serta notes Vanilla Beans &amp; amber yang warm &amp; sweet gourmand di akhir dengan balance yang seimbang. Longevity: 6 hours Sillage: Medium Projection: 2 meters</p> | G402: 1042 | H402: HMNS
A403: 124455 | B403: California Blue Extrait De Parfum | C403: 66fba216e8005543698af0d8 | D403: 229000 | E403: 4.8 | F403: <p>Parfum yang menangkap rasa bebas di hari cerah tepi pantai, dengan nuansa fruity, fresh, dan aquatic.</p><br /><p>NOTES<br>TOP: Lavender, Pear, Grapefruit, Pink Salt<br>MIDDLE: Rhubarb, Water Blossoms, Marine Notes<br>BASE: Moss, Softwood, Caramel</p><br /><p>Cocok buat kamu yang suka parfum fresh aquatic, aromatic, dan slightly sweet!</p><br /><p>- Long-Lasting Scent, tahan lama untuk menemani aktivitasmu<br>- Perfect for Daily Wear, wangi yang pas dan nyaman untuk aktivitas sehari-hari</p> <p>Cara Pakai<br>- Semprot pada titik nadi dengan jarak 15-20 cm<br>- Tunggu hingga kering</p> | G403: 62 | H403: Mykonos
A404: 100375 | B404: Drops of Sunshine Hair & Body Mist | C404: 62c7f51270c7e2af7c6ad720 | D404: 145000 | E404: 4.644274 | F404: <p>Bagaimana kalau kami mengekstraksi matahari? Terinspirasi dari keindahan Dewi Fajar, EᴼS. Sebuah parfum bertipe bunga oriental &amp; gourmand yang menggugah selera. Top notes dibuka dengan wangi coriander yang meningkatkan suasana hati. Lalu muncul keharuman bunga melati yang indah. Hingga akhirnya perjalanan ditutup dengan kenikmatan wangi vanilla.<br><br>Performa<br>Ketahanan: 2 - 3 jam<br>Daya jejak: Medium<br>Proyeksi: 1 - 2 meter</p> | G404: 469 | H404: HMNS
A405: 114834 | B405: Mykonos Black Opera | C405: 66fba216e8005543698af0d8 | D405: 299000 | E405: 4.8259887 | F405: <p>Parfum yang menghadirkan sisi manis dan sensual lewat perpaduan vanilla, coffee, dan warm gourmand notes.</p> <p>NOTES<br>TOP: Vanilla, Orange Blossom, Pink Pepper<br>MIDDLE: Licorice, Jasmine, Almond, Coffee<br>BASE: Cashmere Wood, Jasmine, Vanilla, Patchouli</p> <p>Cocok buat kamu yang suka parfum sweet, creamy, dan seductive!</p> <p>- Long-Lasting Scent, tahan lama untuk menemani aktivitasmu<br>- Perfect for Daily Wear, wangi yang pas dan nyaman untuk aktivitas sehari-hari</p> <p>Cara Pakai<br>- Semprot pada titik nadi dengan jarak 15-20 cm<br>- Tunggu hingga kering</p> | G405: 60 | H405: Mykonos
A406: 114804 | B406: Mykonos Verve EDP | C406: 66fba216e8005543698af0d8 | D406: 179000 | E406: 4.884058 | F406: <p>Parfum yang menghadirkan sisi manis dan feminin lewat perpaduan pear, jasmine, praline, dan vanilla.</p> <p>NOTES<br>TOP: Vanilla, Pear, Blackcurrant<br>MIDDLE: Jasmine, Iris, Orange Blossom<br>BASE: Praline, Vanilla, Tonka Bean</p> <p>Cocok buat kamu yang suka parfum sweet, creamy, dan fruity floral!</p> <p>- Long-Lasting Scent, tahan lama untuk menemani aktivitasmu<br>- Perfect for Daily Wear, wangi yang pas dan nyaman untuk aktivitas sehari-hari</p> <p>Cara Pakai<br>- Semprot pada titik nadi dengan jarak 15-20 cm<br>- Tunggu hingga kering</p> | G406: 24 | H406: Mykonos
... A475: 109668 | B475: Kyoto jazz extrait de Parfume | C475: 658a8e243cca26bc8b2f676b | D475: 329000 | E475: 4.7833333 | F475: <p>Kyoto Jazz terinspirasi dari semangat seni Kyoto yang kreatif, tempat musik dan seni saling bertemu dalam satu ekspresi artistik.</p> <p>NOTES<br>TOP: Matcha, Green Notes, Yuzu, Pear, Bergamot, Cocoa, Cardamom, Lavandin, Ozone<br>MID: Ylang-Ylang, Violet, Beeswax, Orange Blossom, Lily of the Valley, Cassis, Pineapple<br>BASE: Musk, Sandalwood, Amber, Iris, Cashmere, Vanilla, Patchouli, Moss, Labdanum</p> <p>Cocok buat kamu yang suka parfum dengan karakter scent fresh, green, creamy, woody, sophisticated, comforting!</p> <p>- Long-Lasting Scent, tahan lama untuk menemani aktivitasmu<br>- Perfect for Daily Wear, wangi yang pas dan nyaman untuk aktivitas sehari-hari</p> <p>Cara Pakai<br>- Semprot pada titik nadi dengan jarak 15-20 cm<br>- Tunggu hingga kering</p> | G475: 20 | H475: Layr

Sheet top10

Sheet brandmetrics
A1: brand_id | B1: brand_name | C1: product_count | D1: total_reviews | E1: average_rating | F1: minimum_price | G1: maximum_price | H1: average_price | I1: reviews_per_product | J1: products_4_5_plus | K1: products_with_rating | L1: pct_products_4_5_plus | Q1: {={brandmetrics!B1:B55,brandmetrics!C1:C55,brandmetrics!E1:E55,brandmetrics!D1:D55}} -> brand_name | R1: product_count | S1: average_rating | T1: total_reviews
A2: 5d3ac2ffa6992471b7c971d6 | B2: Jarte Beauty | C2: 19 | D2: 93 | E2: 3.3849369 | F2: 189000 | G2: 855000 | H2: 367052.63 | I2: 4.8947368 | J2: 10 | K2: 19 | L2: 52.631579 | Q2: Jarte Beauty | R2: 19 | S2: 3.3849369 | T2: 93
A3: 5d3ac307a6992471b7c97a2d | B3: BLP Beauty | C3: 4 | D3: 74 | E3: 4.7617322 | F3: 289000 | G3: 289000 | H3: 289000 | I3: 18.5 | J3: 4 | K3: 4 | L3: 100 | Q3: BLP Beauty | R3: 4 | S3: 4.7617322 | T3: 74
A4: 5d3ac307a6992471b7c97b2f | B4: Rollover Reaction | C4: 2 | D4: 12 | E4: 3.6666667 | F4: 169000 | G4: 179000 | H4: 174000 | I4: 6 | J4: 1 | K4: 2 | L4: 50 | Q4: Rollover Reaction | R4: 2 | S4: 3.6666667 | T4: 12
A5: 5d3ac307a6992471b7c97b76 | B5: Wardah | C5: 1 | D5: 609 | E5: 4.416181 | F5: 43500 | G5: 43500 | H5: 43500 | I5: 609 | J5: 0 | K5: 1 | L5: 0 | Q5: Wardah | R5: 1 | S5: 4.416181 | T5: 609
A6: 5d3ac307a6992471b7c97bab | B6: Jacquelle Beaute | C6: 6 | D6: 19 | E6: 3.8222222 | F6: 69000 | G6: 288000 | H6: 161166.67 | I6: 3.1666667 | J6: 3 | K6: 6 | L6: 50 | Q6: Jacquelle Beaute | R6: 6 | S6: 3.8222222 | T6: 19
A7: 5db51d092023815654e4cc93 | B7: Scarlett Whitening | C7: 16 | D7: 1244 | E7: 4.8448113 | F7: 67500 | G7: 75000 | H7: 72656.25 | I7: 77.75 | J7: 16 | K7: 16 | L7: 100 | Q7: Scarlett Whitening | R7: 16 | S7: 4.8448113 | T7: 1244
A8: 5f5640bc311107db64724988 | B8: Careso | C8: 22 | D8: 2604 | E8: 4.6272988 | F8: 54000 | G8: 209000 | H8: 107727.27 | I8: 118.36364 | J8: 18 | K8: 22 | L8: 81.818182 | Q8: Careso | R8: 22 | S8: 4.6272988 | T8: 2604
A9: 60d4e2c6443396b9504d4beb | B9: SAFF & Co | C9: 27 | D9: 8171 | E9: 4.7940261 | F9: 199000 | G9: 349000 | H9: 304555.56 | I9: 302.62963 | J9: 27 | K9: 27 | L9: 100 | Q9: SAFF & Co | R9: 27 | S9: 4.7940261 | T9: 8171
A10: 62bbfd4abd4201d78fc0e8f5 | B10: Bonavie | C10: 16 | D10: 2724 | E10: 4.631903 | F10: 34000 | G10: 115000 | H10: 76625 | I10: 170.25 | J10: 14 | K10: 16 | L10: 87.5 | Q10: Bonavie | R10: 16 | S10: 4.631903 | T10: 2724
A11: 62c7f51270c7e2af7c6ad720 | B11: HMNS | C11: 23 | D11: 5624 | E11: 4.1372498 | F11: 139000 | G11: 525000 | H11: 341826.09 | I11: 244.52174 | J11: 20 | K11: 23 | L11: 86.956522 | Q11: HMNS | R11: 23 | S11: 4.1372498 | T11: 5624
A12: 62fb16f36d42e66ec212086f | B12: Verites | C12: 29 | D12: 379 | E12: 3.2607412 | F12: 209000 | G12: 329000 | H12: 270034.48 | I12: 13.068966 | J12: 20 | K12: 29 | L12: 68.965517 | Q12: Verites | R12: 29 | S12: 3.2607412 | T12: 379
A13: 630c79bfa09d276df7478c18 | B13: Alchemist Fragrance | C13: 8 | D13: 783 | E13: 3.9195472 | F13: 199000 | G13: 679000 | H13: 337750 | I13: 97.875 | J13: 4 | K13: 8 | L13: 50 | Q13: Alchemist Fragrance | R13: 8 | S13: 3.9195472 | T13: 783
... A46: 6a4cb2ea215496274f7b9d51 | B46: Barsten | C46: 2 | D46: 0 | E46: 0 | F46: 209000 | G46: 209000 | H46: 209000 | I46: 0 | J46: 0 | K46: 2 | L46: 0 | Q46: Barsten | R46: 2 | S46: 0 | T46: 0

Sheet rating
A1: rating | B1: review_count | C1: percentage | E1: rating_group | F1: countgroup
A2: 1 | B2: 15 | C2: 0.049196458 | E2: 1–1.9 | F2: =SUMIF(rating[rating],">=1",rating[review_count])-SUMIF(rating[rating],">=2",rating[review_count]) -> 28
A3: 1.3 | B3: 4 | C3: 0.013119055 | E3: 2–2.9 | F3: =SUMIF(rating[rating],">=2",rating[review_count])-SUMIF(rating[rating],">=3",rating[review_count]) -> 90
A4: 1.7 | B4: 9 | C4: 0.029517875 | E4: 3–3.9 | F4: =SUMIF($A$2:$A$23,">=3",$B$2:$B$23)-SUMIF($A$2:$A$23,">=4",$B$2:$B$23) -> 1210
A5: 2 | B5: 18 | C5: 0.059035749 | E5: 4–4.9 | F5: =SUMIF(rating[rating],">=4",rating[review_count])-SUMIF(rating[rating],">=5",rating[review_count]) -> 10079
A6: 2.3 | B6: 24 | C6: 0.078714333 | E6: 5 | F6: =SUMIF(rating[rating],5,rating[review_count]) -> 19083
A7: 2.5 | B7: 1 | C7: 0.0032797639
A8: 2.7 | B8: 47 | C8: 0.1541489
A9: 3 | B9: 180 | C9: 0.59035749
A10: 3.3 | B10: 301 | C10: 0.98720892
A11: 3.3333333 | B11: 1 | C11: 0.0032797639
A12: 3.5 | B12: 1 | C12: 0.0032797639
A13: 3.6666667 | B13: 2 | C13: 0.0065595277
A14: 3.7 | B14: 724 | C14: 2.374549
A15: 3.8 | B15: 1 | C15: 0.0032797639
A16: 4 | B16: 2230 | C16: 7.3138734
A17: 4.3 | B17: 3186 | C17: 10.449328
A18: 4.3333333 | B18: 8 | C18: 0.026238111
... A23: 5 | B23: 19083 | C23: 62.587734

Sheet brands
A1: brand_id | B1: brand_name | C1: products_count | D1: Column 1
A2: 65b72e108291fedb80cbd999 | B2: AA TEst | C2: =COUNTIF(products!C:C, brands!A2) -> 0 | D2: =IFERROR(__xludf.DUMMYFUNCTION("SUMPRODUCT(COUNTIF(reviews!B:B, FILTER(products!A:A, products!C:C = A2)))"),0.0) -> 0
A3: 630c79bfa09d276df7478c18 | B3: Alchemist Fragrance | C3: =COUNTIF(products!C:C, brands!A3) -> 8 | D3: =IFERROR(__xludf.DUMMYFUNCTION("SUMPRODUCT(COUNTIF(reviews!B:B, FILTER(products!A:A, products!C:C = A3)))"),783.0) -> 783
A4: 678f22b3bf9a94d16f30d103 | B4: Alt perfumery | C4: =COUNTIF(products!C:C, brands!A4) -> 10 | D4: =IFERROR(__xludf.DUMMYFUNCTION("SUMPRODUCT(COUNTIF(reviews!B:B, FILTER(products!A:A, products!C:C = A4)))"),70.0) -> 70
A5: 686f7faa358423a01d1b1f32 | B5: ATSIRI | C5: =COUNTIF(products!C:C, brands!A5) -> 2 | D5: =IFERROR(__xludf.DUMMYFUNCTION("SUMPRODUCT(COUNTIF(reviews!B:B, FILTER(products!A:A, products!C:C = A5)))"),0.0) -> 0
A6: 689c00257493d86323be7038 | B6: Barbie | C6: =COUNTIF(products!C:C, brands!A6) -> 3 | D6: =IFERROR(__xludf.DUMMYFUNCTION("SUMPRODUCT(COUNTIF(reviews!B:B, FILTER(products!A:A, products!C:C = A6)))"),24.0) -> 24
A7: 6a4cb2ea215496274f7b9d51 | B7: Barsten | C7: =COUNTIF(products!C:C, brands!A7) -> 2 | D7: =IFERROR(__xludf.DUMMYFUNCTION("SUMPRODUCT(COUNTIF(reviews!B:B, FILTER(products!A:A, products!C:C = A7)))"),0.0) -> 0
A8: 6492bb87ec4713a4402897b4 | B8: Beauty Secrets | C8: =COUNTIF(products!C:C, brands!A8) -> 7 | D8: =IFERROR(__xludf.DUMMYFUNCTION("SUMPRODUCT(COUNTIF(reviews!B:B, FILTER(products!A:A, products!C:C = A8)))"),278.0) -> 278
A9: 677f9e29bd1dd357b29899bc | B9: BESTIE PINK RUN | C9: =COUNTIF(products!C:C, brands!A9) -> 1 | D9: =IFERROR(__xludf.DUMMYFUNCTION("SUMPRODUCT(COUNTIF(reviews!B:B, FILTER(products!A:A, products!C:C = A9)))"),0.0) -> 0
A10: 6a2942986a9dc81f99a07ab8 | B10: BLACKSTAG | C10: =COUNTIF(products!C:C, brands!A10) -> 6 | D10: =IFERROR(__xludf.DUMMYFUNCTION("SUMPRODUCT(COUNTIF(reviews!B:B, FILTER(products!A:A, products!C:C = A10)))"),0.0) -> 0
A11: 5d3ac307a6992471b7c97a2d | B11: BLP Beauty | C11: =COUNTIF(products!C:C, brands!A11) -> 4 | D11: =IFERROR(__xludf.DUMMYFUNCTION("SUMPRODUCT(COUNTIF(reviews!B:B, FILTER(products!A:A, products!C:C = A11)))"),74.0) -> 74
A12: 684fc0d7d4bf7febcf441ede | B12: BODIBREZE | C12: =COUNTIF(products!C:C, brands!A12) -> 8 | D12: =IFERROR(__xludf.DUMMYFUNCTION("SUMPRODUCT(COUNTIF(reviews!B:B, FILTER(products!A:A, products!C:C = A12)))"),158.0) -> 158
A13: 62bbfd4abd4201d78fc0e8f5 | B13: Bonavie | C13: =COUNTIF(products!C:C, brands!A13) -> 16 | D13: =IFERROR(__xludf.DUMMYFUNCTION("SUMPRODUCT(COUNTIF(reviews!B:B, FILTER(products!A:A, products!C:C = A13)))"),2724.0) -> 2724
A14: 5f5640bc311107db64724988 | B14: Careso | C14: =COUNTIF(products!C:C, brands!A14) -> 22 | D14: =IFERROR(__xludf.DUMMYFUNCTION("SUMPRODUCT(COUNTIF(reviews!B:B, FILTER(products!A:A, products!C:C = A14)))"),2604.0) -> 2604
A15: 67778a892a80de5b41843ff8 | B15: CONSTANT | C15: =COUNTIF(products!C:C, brands!A15) -> 0 | D15: =IFERROR(__xludf.DUMMYFUNCTION("SUMPRODUCT(COUNTIF(reviews!B:B, FILTER(products!A:A, products!C:C = A15)))"),0.0) -> 0
A16: 687f0e912e6e4dd7b8ae25dd | B16: Crusita | C16: =COUNTIF(products!C:C, brands!A16) -> 10 | D16: =IFERROR(__xludf.DUMMYFUNCTION("SUMPRODUCT(COUNTIF(reviews!B:B, FILTER(products!A:A, products!C:C = A16)))"),469.0) -> 469
A17: 696f319a12cb95e5b7ae13b3 | B17: De Antoine | C17: =COUNTIF(products!C:C, brands!A17) -> 10 | D17: =IFERROR(__xludf.DUMMYFUNCTION("SUMPRODUCT(COUNTIF(reviews!B:B, FILTER(products!A:A, products!C:C = A17)))"),9.0) -> 9
A18: 69292226555238423bb4eecf | B18: Earth Love Life | C18: =COUNTIF(products!C:C, brands!A18) -> 5 | D18: =IFERROR(__xludf.DUMMYFUNCTION("SUMPRODUCT(COUNTIF(reviews!B:B, FILTER(products!A:A, products!C:C = A18)))"),13.0) -> 13
A19: 63f33afa031c4c49121df81c | B19: Elmer | C19: =COUNTIF(products!C:C, brands!A19) -> 5 | D19: =IFERROR(__xludf.DUMMYFUNCTION("SUMPRODUCT(COUNTIF(reviews!B:B, FILTER(products!A:A, products!C:C = A19)))"),148.0) -> 148
A20: 65b76e306a21aad7d8a51fd1 | B20: EONA | C20: =COUNTIF(products!C:C, brands!A20) -> 0 | D20: =IFERROR(__xludf.DUMMYFUNCTION("SUMPRODUCT(COUNTIF(reviews!B:B, FILTER(products!A:A, products!C:C = A20)))"),0.0) -> 0
A21: 6259228f6bfc2e5818b86f27 | B21: Esscentials Indonesia | C21: =COUNTIF(products!C:C, brands!A21) -> 0 | D21: =IFERROR(__xludf.DUMMYFUNCTION("SUMPRODUCT(COUNTIF(reviews!B:B, FILTER(products!A:A, products!C:C = A21)))"),0.0) -> 0
A22: 6311def8368f94cfd772b44d | B22: Fordive | C22: =COUNTIF(products!C:C, brands!A22) -> 6 | D22: =IFERROR(__xludf.DUMMYFUNCTION("SUMPRODUCT(COUNTIF(reviews!B:B, FILTER(products!A:A, products!C:C = A22)))"),152.0) -> 152
A23: 62c7f51270c7e2af7c6ad720 | B23: HMNS | C23: =COUNTIF(products!C:C, brands!A23) -> 23 | D23: =IFERROR(__xludf.DUMMYFUNCTION("SUMPRODUCT(COUNTIF(reviews!B:B, FILTER(products!A:A, products!C:C = A23)))"),5624.0) -> 5624
A24: 68cb7c30436c5829a063d777 | B24: IGNIO | C24: =COUNTIF(products!C:C, brands!A24) -> 3 | D24: =IFERROR(__xludf.DUMMYFUNCTION("SUMPRODUCT(COUNTIF(reviews!B:B, FILTER(products!A:A, products!C:C = A24)))"),128.0) -> 128
A25: 667d3cc467565050b7424bc9 | B25: In The Mood For | C25: =COUNTIF(products!C:C, brands!A25) -> 46 | D25: =IFERROR(__xludf.DUMMYFUNCTION("SUMPRODUCT(COUNTIF(reviews!B:B, FILTER(products!A:A, products!C:C = A25)))"),2044.0) -> 2044
A26: 66a9acee27c22fdce5c62563 | B26: ISLAN | C26: =COUNTIF(products!C:C, brands!A26) -> 4 | D26: =IFERROR(__xludf.DUMMYFUNCTION("SUMPRODUCT(COUNTIF(reviews!B:B, FILTER(products!A:A, products!C:C = A26)))"),41.0) -> 41
A27: 65b325069eda6e77244b9aa3 | B27: ISWHITE | C27: =COUNTIF(products!C:C, brands!A27) -> 6 | D27: =IFERROR(__xludf.DUMMYFUNCTION("SUMPRODUCT(COUNTIF(reviews!B:B, FILTER(products!A:A, products!C:C = A27)))"),6.0) -> 6
A28: 5d3ac307a6992471b7c97bab | B28: Jacquelle Beaute | C28: =COUNTIF(products!C:C, brands!A28) -> 6 | D28: =IFERROR(__xludf.DUMMYFUNCTION("SUMPRODUCT(COUNTIF(reviews!B:B, FILTER(products!A:A, products!C:C = A28)))"),19.0) -> 19
A29: 5d3ac2ffa6992471b7c971d6 | B29: Jarte Beauty | C29: =COUNTIF(products!C:C, brands!A29) -> 19 | D29: =IFERROR(__xludf.DUMMYFUNCTION("SUMPRODUCT(COUNTIF(reviews!B:B, FILTER(products!A:A, products!C:C = A29)))"),93.0) -> 93
A30: 657ad93e28f41e975c8a966c | B30: Kahf | C30: =COUNTIF(products!C:C, brands!A30) -> 14 | D30: =IFERROR(__xludf.DUMMYFUNCTION("SUMPRODUCT(COUNTIF(reviews!B:B, FILTER(products!A:A, products!C:C = A30)))"),27.0) -> 27
A31: 639fccbc887ae13b38ea4221 | B31: Kitschy | C31: =COUNTIF(products!C:C, brands!A31) -> 0 | D31: =IFERROR(__xludf.DUMMYFUNCTION("SUMPRODUCT(COUNTIF(reviews!B:B, FILTER(products!A:A, products!C:C = A31)))"),0.0) -> 0
A32: 62cadbc86429fa4da043c7b7 | B32: Lavojoy | C32: =COUNTIF(products!C:C, brands!A32) -> 0 | D32: =IFERROR(__xludf.DUMMYFUNCTION("SUMPRODUCT(COUNTIF(reviews!B:B, FILTER(products!A:A, products!C:C = A32)))"),0.0) -> 0
A33: 658a8e243cca26bc8b2f676b | B33: Layr | C33: =COUNTIF(products!C:C, brands!A33) -> 4 | D33: =IFERROR(__xludf.DUMMYFUNCTION("SUMPRODUCT(COUNTIF(reviews!B:B, FILTER(products!A:A, products!C:C = A33)))"),130.0) -> 130
A34: 6512b419e2ce9e1e8739b219 | B34: Lilith and Eve | C34: =COUNTIF(products!C:C, brands!A34) -> 0 | D34: =IFERROR(__xludf.DUMMYFUNCTION("SUMPRODUCT(COUNTIF(reviews!B:B, FILTER(products!A:A, products!C:C = A34)))"),0.0) -> 0
A35: 5d3ac306a6992471b7c97824 | B35: Luxcrime | C35: =COUNTIF(products!C:C, brands!A35) -> 0 | D35: =IFERROR(__xludf.DUMMYFUNCTION("SUMPRODUCT(COUNTIF(reviews!B:B, FILTER(products!A:A, products!C:C = A35)))"),0.0) -> 0
A36: 654070018fac4010da648abf | B36: Mercredi | C36: =COUNTIF(products!C:C, brands!A36) -> 8 | D36: =IFERROR(__xludf.DUMMYFUNCTION("SUMPRODUCT(COUNTIF(reviews!B:B, FILTER(products!A:A, products!C:C = A36)))"),7.0) -> 7
A37: 690b205bb7ffaa4cb6a4e8a8 | B37: MMRS | C37: =COUNTIF(products!C:C, brands!A37) -> 6 | D37: =IFERROR(__xludf.DUMMYFUNCTION("SUMPRODUCT(COUNTIF(reviews!B:B, FILTER(products!A:A, products!C:C = A37)))"),1.0) -> 1
A38: 610a4baac3617d6f38595620 | B38: Mother of Pearl | C38: =COUNTIF(products!C:C, brands!A38) -> 0 | D38: =IFERROR(__xludf.DUMMYFUNCTION("SUMPRODUCT(COUNTIF(reviews!B:B, FILTER(products!A:A, products!C:C = A38)))"),0.0) -> 0
A39: 66fba216e8005543698af0d8 | B39: Mykonos | C39: =COUNTIF(products!C:C, brands!A39) -> 37 | D39: =IFERROR(__xludf.DUMMYFUNCTION("SUMPRODUCT(COUNTIF(reviews!B:B, FILTER(products!A:A, products!C:C = A39)))"),1283.0) -> 1283
A40: 6979dfc48d450be00450df29 | B40: Nevernot Official | C40: =COUNTIF(products!C:C, brands!A40) -> 11 | D40: =IFERROR(__xludf.DUMMYFUNCTION("SUMPRODUCT(COUNTIF(reviews!B:B, FILTER(products!A:A, products!C:C = A40)))"),16.0) -> 16
A41: 655dc43d5d8272b99f510b3b | B41: Onix | C41: =COUNTIF(products!C:C, brands!A41) -> 5 | D41: =IFERROR(__xludf.DUMMYFUNCTION("SUMPRODUCT(COUNTIF(reviews!B:B, FILTER(products!A:A, products!C:C = A41)))"),98.0) -> 98
A42: 64bf8ffd47133c15bf961d74 | B42: Project 1945 | C42: =COUNTIF(products!C:C, brands!A42) -> 12 | D42: =IFERROR(__xludf.DUMMYFUNCTION("SUMPRODUCT(COUNTIF(reviews!B:B, FILTER(products!A:A, products!C:C = A42)))"),421.0) -> 421
A43: 66ed2767c46f3a83999c0374 | B43: Rahasia Fragrance | C43: =COUNTIF(products!C:C, brands!A43) -> 12 | D43: =IFERROR(__xludf.DUMMYFUNCTION("SUMPRODUCT(COUNTIF(reviews!B:B, FILTER(products!A:A, products!C:C = A43)))"),172.0) -> 172
A44: 6453667949508849cfde4a96 | B44: Raine Beauty | C44: =COUNTIF(products!C:C, brands!A44) -> 1 | D44: =IFERROR(__xludf.DUMMYFUNCTION("SUMPRODUCT(COUNTIF(reviews!B:B, FILTER(products!A:A, products!C:C = A44)))"),9.0) -> 9
A45: 5d3ac307a6992471b7c97b2f | B45: Rollover Reaction | C45: =COUNTIF(products!C:C, brands!A45) -> 2 | D45: =IFERROR(__xludf.DUMMYFUNCTION("SUMPRODUCT(COUNTIF(reviews!B:B, FILTER(products!A:A, products!C:C = A45)))"),12.0) -> 12
A46: 60d4e2c6443396b9504d4beb | B46: SAFF & Co | C46: =COUNTIF(products!C:C, brands!A46) -> 27 | D46: =IFERROR(__xludf.DUMMYFUNCTION("SUMPRODUCT(COUNTIF(reviews!B:B, FILTER(products!A:A, products!C:C = A46)))"),8171.0) -> 8171
A47: 69200f1ca1ea6f13126c7ba9 | B47: SAKA Perfumery | C47: =COUNTIF(products!C:C, brands!A47) -> 5 | D47: =IFERROR(__xludf.DUMMYFUNCTION("SUMPRODUCT(COUNTIF(reviews!B:B, FILTER(products!A:A, products!C:C = A47)))"),11.0) -> 11
A48: 64250c29b46a7a1d02cebc8e | B48: SATELLITE OF GLOW | C48: =COUNTIF(products!C:C, brands!A48) -> 7 | D48: =IFERROR(__xludf.DUMMYFUNCTION("SUMPRODUCT(COUNTIF(reviews!B:B, FILTER(products!A:A, products!C:C = A48)))"),47.0) -> 47
A49: 5db51d092023815654e4cc93 | B49: Scarlett Whitening | C49: =COUNTIF(products!C:C, brands!A49) -> 16 | D49: =IFERROR(__xludf.DUMMYFUNCTION("SUMPRODUCT(COUNTIF(reviews!B:B, FILTER(products!A:A, products!C:C = A49)))"),1244.0) -> 1244
A50: 67bbeaee630f7e48677f515a | B50: SLAVINA | C50: =COUNTIF(products!C:C, brands!A50) -> 14 | D50: =IFERROR(__xludf.DUMMYFUNCTION("SUMPRODUCT(COUNTIF(reviews!B:B, FILTER(products!A:A, products!C:C = A50)))"),89.0) -> 89
A51: 6510fae507d9f80342bc6d05 | B51: Speaks To Me | C51: =COUNTIF(products!C:C, brands!A51) -> 17 | D51: =IFERROR(__xludf.DUMMYFUNCTION("SUMPRODUCT(COUNTIF(reviews!B:B, FILTER(products!A:A, products!C:C = A51)))"),2217.0) -> 2217
A52: 6a38a4f9981964fc62a818a4 | B52: Velixir Parfums | C52: =COUNTIF(products!C:C, brands!A52) -> 8 | D52: =IFERROR(__xludf.DUMMYFUNCTION("SUMPRODUCT(COUNTIF(reviews!B:B, FILTER(products!A:A, products!C:C = A52)))"),16.0) -> 16
A53: 62fb16f36d42e66ec212086f | B53: Verites | C53: =COUNTIF(products!C:C, brands!A53) -> 29 | D53: =IFERROR(__xludf.DUMMYFUNCTION("SUMPRODUCT(COUNTIF(reviews!B:B, FILTER(products!A:A, products!C:C = A53)))"),379.0) -> 379
A54: 5d3ac307a6992471b7c97b76 | B54: Wardah | C54: =COUNTIF(products!C:C, brands!A54) -> 1 | D54: =IFERROR(__xludf.DUMMYFUNCTION("SUMPRODUCT(COUNTIF(reviews!B:B, FILTER(products!A:A, products!C:C = A54)))"),609.0) -> 609
A55: 662b56b473a9ec785fc0b744 | B55: YN Perfumery | C55: =COUNTIF(products!C:C, brands!A55) -> 6 | D55: =IFERROR(__xludf.DUMMYFUNCTION("SUMPRODUCT(COUNTIF(reviews!B:B, FILTER(products!A:A, products!C:C = A55)))"),12.0) -> 12

Sheet products
A1: product_id | B1: product_name | C1: brand_id | D1: price | E1: avg_rating | F1: description
A2: 110247 | B2: HMNS x Tsana Fragrance Mist - Elea | C2: 62c7f51270c7e2af7c6ad720 | D2: 185000 | E2: 4.743803e+16 | F2: <p>Pertama kali kamu bertemu Elea nanti, tutup mata kamu. Kamu akan dengan mudah mengenalinya dari rambut panjangnya, dan wangi bunga magnolianya. Yang cantik &amp; terasa hijau seperti magnolia yang baru saja dipetik.<br>Sebentar setelah kamu di dekatnya, kamu sadar kalau Elea lebih kompleks dari setangkai bunga magnolia. Elea seperti puluhan kombinasi bunga putih yang terikat dengan madu dan minyak biji ambrette. Dia terasa dekat, terasa hangat.<br>Dan untuk sesaat dalam waktu yang panjang, kamu sadar kalau akhirnya..<br>Kamu gak sendirian.<br>[Product Detail]<br>Type: Eau de Toilette<br>Group: White Floral<br>Size: 250 ml<br>Longevity: 2 - 3 hours<br>Sillage: Medium<br>Projection: 1 - 2.5 meters</p>
A3: 117020 | B3: IRAI LEIMA - Extrait de Parfum | C3: 60d4e2c6443396b9504d4beb | D3: 349000 | E3: 4.8344444e+15 | F3: <p>Parfum aquatic yang membawa sensasi udara laut segar, air yang tenang, dan drydown hangat yang terasa lembut di kulit.</p><br /><p>NOTES<br>TOP: Cassis Buds, Dalanghita, Pink Pepper<br>MID: Duchesse de Nemours, Water Iris, Raat ki Rani<br>BASE: Warm Musky Notes</p><br /><p>Cocok buat kamu yang suka parfum aquatic floral yang fresh dan soft!</p><br /><p>- Long-Lasting Scent, tahan lama untuk menemani aktivitasmu<br>- Perfect for Daily Wear, wangi yang pas dan nyaman untuk aktivitas sehari-hari</p><br /><p>Cara Pakai<br>- Semprot pada titik nadi dengan jarak 15-20 cm<br>- Tunggu hingga kering</p>
A4: 98385 | B4: S.O.T.B - Extrait de Parfum | C4: 60d4e2c6443396b9504d4beb | D4: 349000 | E4: 4.857915e+16 | F4: <p>Parfum yang menangkap summer dream: kulit yang sun-kissed, beach breeze, dan suasana tropical yang fun sepanjang hari.</p><br /><p>NOTES<br>TOP: Mandarin<br>MID: Sweet Floral Notes<br>BASE: Vanilla Musk</p><br /><p>Cocok buat kamu yang suka parfum tropical floral yang fresh dan creamy!</p><br /><p>- Long-Lasting Scent, tahan lama untuk menemani aktivitasmu<br>- Perfect for Daily Wear, wangi yang pas dan nyaman untuk aktivitas sehari-hari</p><br /><p>Cara Pakai<br>- Semprot pada titik nadi dengan jarak 15-20 cm<br>- Tunggu hingga kering</p>
A5: 118066 | B5: Velvet Rouge Extrait De Parfum | C5: 5db51d092023815654e4cc93 | D5: 75000 | E5: 4.8662485e+15 | F5: <p>Scarlett Whitening Eau De Parfum 30ml<br>Scarlett Whitening Eau De Parfum a Perfection untuk berikan kesegaran dan keharuman mewah dalam setiap semprotan dengan kemasan yang Ready To Go cocok untuk temani harimu, mudah dibawa kemana pun dan kapan pun tanpa takut pecah! dengan wangi yang mewah<br>Luxurious Scent with Affordable Price.</p>
A6: 124504 | B6: Cotton Hug Extrait De Parfum | C6: 5db51d092023815654e4cc93 | D6: 67500 | E6: 4.8509666e+15 | F6: <p>Jenis Aroma : Woody Powdery <br><br>Cotton Hug menggambarkan sosok yang tenang, lembut, dan elegan tanpa usaha berlebihan. Aroma bersih dari aldehyde, orange, dan sentuhan coconut membuka kesan fresh yang menenangkan, seperti pakaian hangat yang baru dijemur di bawah matahari pagi. Di tengahnya, perpaduan muguet, violet, dan orchid menghadirkan keanggunan feminin yang lembut. Lapisan akhir moss, sandalwood, musk, dan amber memberi sentuhan hangat dan powdery, membungkus lembut seperti pelukan penuh ketenangan. <br><br>Top Notes : Aldehyde, Ylang Ylang, Orange, Coconut, Berries <br>Heart Notes : Muguet, Rose, Orange Flower, Violet, Orchid <br>Bottom Notes : Moss, Sandalwood, Musk, Amber, Tonka</p>
A7: 113698 | B7: Cloud Mist - Annabel Lee | C7: 60d4e2c6443396b9504d4beb | D7: 199000 | E7: 4.7735507e+15 | F7: <p>Annabel Lee menangkap nostalgia pertemuan awal, menggemakan keindahan mentah dan keajaiban tak terucapkan dari hati muda yang terjalin dalam kepolosan cinta pertama. Dari luapan emosi yang memusingkan hingga kepedihan kenaifan yang manis, syair-syair ini membisikkan kisah dramatis tentang awal yang lembut dan penemuan yang menggetarkan hati.</p><p></p><p>CHARACTER : Floral, Fruity, Gourmand</p><p>Top Notes | Iced lychee tea, Pear, Petalia</p><p>Middle Notes | Akigalawood, Roseraie de l'Hay, Cashmeran </p><p>Dry-down Notes | Crème de framboise, Amber "</p>
A8: 107813 | B8: Xocolatl - Extrait De Parfum | C8: 60d4e2c6443396b9504d4beb | D8: 349000 | E8: 4.8445251e+15 | F8: <p>Parfum gourmand yang terinspirasi dari hot chocolate pertama, dipadukan mandarin manis dan heliotrope creamy yang playful.</p><br /><p>NOTES<br>TOP: Sweet Mandarin<br>MID: Heliotrope<br>BASE: Creamy Gourmand Notes</p><br /><p>Cocok buat kamu yang suka parfum chocolate gourmand yang sweet dan creamy!</p><br /><p>- Long-Lasting Scent, tahan lama untuk menemani aktivitasmu<br>- Perfect for Daily Wear, wangi yang pas dan nyaman untuk aktivitas sehari-hari</p><br /><p>Cara Pakai<br>- Semprot pada titik nadi dengan jarak 15-20 cm<br>- Tunggu hingga kering</p>
A9: 101486 | B9: Body Mist - Crème Canele | C9: 62bbfd4abd4201d78fc0e8f5 | D9: 34000 | E9: 4.6795062e+15 | F9: <p>Crème Canele menghadirkan aroma vanilla yang manis dan addictive, berpadu dengan karakter cheerful, indulging, dan sensual modern.</p> <p>NOTES<br>TOP: Orange Blossom, Pear, Pink Pepper<br>MID: Jasmine, Rose, Freesia<br>BASE: Vanilla, Patchouli, Cedar, Musk</p> <p>Cocok buat kamu yang suka parfum warm vanilla yang sweet, spicy, dan gourmand!</p> <p>- Long-Lasting Scent, tahan lama untuk menemani aktivitasmu<br>- Perfect for Daily Wear, wangi yang pas dan nyaman untuk aktivitas sehari-hari</p> <p>Cara Pakai<br>- Semprot pada titik nadi dengan jarak 15-20 cm<br>- Tunggu hingga kering</p>
A10: 124503 | B10: Sweetie Love Extrait De Parfum | C10: 5db51d092023815654e4cc93 | D10: 67500 | E10: 4.9111111e+15 | F10: <p>Jenis Aroma : Fruity Floral<br><br>Sweetie Love memancarkan kepribadian yang ceria, youthful, dan penuh cinta. Dibuka dengan aroma manis caramel, segarnya apple dan green pear, menghadirkan kesan playful sejak semprotan pertama. Di tengahnya, perpaduan magnolia, rose, dan sedikit licorice memberi sentuhan feminin yang lembut dan memikat. Ditutup dengan musk dan amber yang hangat, meninggalkan jejak manis yang romantis dan bertahan lama, semanis momen jatuh cinta pertama kali.<br><br>Top Notes : Caramel, Apple, Green Pear<br>Heart Notes : Licorice, Magnolia, Rose<br>Bottom Notes : Musk, Amber</p>
A11: 109448 | B11: Scarlett Eau De Parfume Sweet Memories | C11: 5db51d092023815654e4cc93 | D11: 75000 | E11: 4.8341443e+15 | F11: <p>Scarlett Parfume Sweet Memories EDP 30 ml<br>Scarlett Whitening Eau De Parfum Sweet Memories Untuk berikan kesegaran dan keharuman mewah dalam setiap semprotan dengan kemasan yang Ready To Go cocok untuk temani harimu, mudah dibawa kemana pun dan kapan pun tanpa takut pecah! dengan wangi Amber Fougere yang menjadikan parfum ini mempunyai wangi yang mewah.<br><br>Luxurious Scent with Affordable Price.<br>Gender - Unisex | Woman<br>Top Notes - Egyptian Balsam, Grapefruit, Damask Rose<br>Middle Notes - Vanilla, Honeysuckle, Jasmine, Peach<br>Base Notes - Musky, Cashmeran, Amber</p>
A12: 109449 | B12: Scarlett Eau De Parfume Dreamy | C12: 5db51d092023815654e4cc93 | D12: 75000 | E12: 4.8687235e+15 | F12: <p>Scarlett Parfume Dreamy EDP 30 ml<br>Scarlett Whitening Eau De Parfum Dreamy Untuk berikan kesegaran dan keharuman mewah dalam setiap semprotan dengan kemasan yang Ready To Go cocok untuk temani harimu, mudah dibawa kemana pun dan kapan pun tanpa takut pecah! dengan wangi floral white Floral Ambery yang menjadikan parfum ini mempunyai wangi yang mewah.<br><br>Luxurious Scent with Affordable Price.<br>Gender - Unisex | Woman<br>Top Notes - Bergamot, Mandarin, Ginger, Pear<br>Middle Notes - Jasmine, Tuberose, Orange Flower, Gourmand<br>Base Notes - Amber Dry, Cashmeran, Heliotrope, Vanilla</p>
A13: 114830 | B13: Mykonos Satin Blanc | C13: 66fba216e8005543698af0d8 | D13: 379000 | E13: 4.8845093e+15 | F13: <p>Parfum yang menghadirkan kesan clean dan modern lewat fresh woody aromatic notes yang elegan.</p> <p>NOTES<br>TOP: Bergamot, Black Pepper, Green Apple<br>MIDDLE: Cedar Wood, Jasmine Tea, Floral Bouquet, Aquatic Notes<br>BASE: White Amber, Tonka Bean, Vanilla</p> <p>Cocok buat kamu yang suka parfum fresh dan elegant!</p> <p>- Long-Lasting Scent, tahan lama untuk menemani aktivitasmu<br>- Perfect for Daily Wear, wangi yang pas dan nyaman untuk aktivitas sehari-hari</p> <p>Cara Pakai<br>- Semprot pada titik nadi dengan jarak 15-20 cm<br>- Tunggu hingga kering</p>
... A99: 126320 | B99: Sahara Mirage Extrait De Parfum | C99: 5db51d092023815654e4cc93 | D99: 67500 | E99: 4.5555556e+15 | F99: <p>Scarlett Whitening Extrait De Parfum by world class perfumer, long-lasting up to 16 hours, and perfect for daily-use.<br><br>Luxurious Scent with Affordable Price!<br><br><strong>Scarlett Whitening Extrait de Parfum SAHARA MIRAGE</strong><br>Gender - Woman <br>Floral + Fruity + Woody<br>Top notes: Passionfruit, Peach<br>Heart Notes: Geranium, Jasmine<br>Bottom Notes: Vetiver, Patchouli, Dry Amber</p>
A100: 122362 | B100: Slavina Fine Fragrance Mist Shooting Star | C100: 67bbeaee630f7e48677f515a | D100: 119000 | E100: 5.0 | F100: <p>Aroma khas manis dari perpaduan berries dan floral. Kombinasi Vanilla dan Musk pada Base noted menciptakan aroma yang lembut dan tahan lama</p>
A101: 122645 | B101: Eclipse Eau De Parfum | C101: 68cb7c30436c5829a063d777 | D101: 149000 | E101: 4.8805031e+15 | F101: <p>Eclipse Eau De Parfum adalah parfum aromatic woody yang fresh dan sophisticated.</p> <p>NOTES<br>TOP: Juniper Berry, Lemon, Black Pepper<br>MID: Grass, Elemi, Geranium<br>BASE: Amber, Wood, Musk</p> <p>Cocok buat kamu yang suka parfum aromatic woody yang fresh, spicy, dan sophisticated!</p> <p>- Long-Lasting Scent, tahan lama untuk menemani aktivitasmu<br>- Perfect for Daily Wear, wangi yang pas dan nyaman untuk aktivitas sehari-hari</p> <p>Cara Pakai<br>- Semprot pada titik nadi dengan jarak 15-20 cm<br>- Tunggu hingga kering</p>
A102: 107812 | B102: Las Pozas - Extrait De Parfum | C102: 60d4e2c6443396b9504d4beb | D102: 349000 | E102: 4.8195876e+15 | F102: <p>Parfum yang membawamu menyusuri hutan tropis yang tenang, saat angin, kicau burung, dan nuansa woody creamy terasa surreal namun grounding.</p> <p>NOTES<br>- Angel’s Trumpet<br>- Forest Accord<br>- Cashmeran<br>- Sumatran Benzoin, Sandalwood</p> <p>Cocok buat kamu yang suka parfum woody creamy yang earthy dan calming!</p> <p>- Long-Lasting Scent, tahan lama untuk menemani aktivitasmu<br>- Perfect for Daily Wear, wangi yang pas dan nyaman untuk aktivitas sehari-hari</p> <p>Cara Pakai<br>- Semprot pada titik nadi dengan jarak 15-20 cm<br>- Tunggu hingga kering</p>
A103: 122644 | B103: Spark Eau De Parfum | C103: 68cb7c30436c5829a063d777 | D103: 149000 | E103: 481981981981982 | F103: <p>Spark Eau De Parfum adalah parfum citrus aquatic yang fresh dan energizing untuk aktivitas sehari-hari.</p> <p>NOTES<br>TOP: Mandarin, Orange<br>MID: Lavender, Aquatic Accord<br>BASE: Patchouli, Red Cedar, Ambrox</p> <p>Cocok buat kamu yang suka parfum citrus fresh yang clean, energetic, dan modern!</p> <p>- Long-Lasting Scent, tahan lama untuk menemani aktivitasmu<br>- Perfect for Daily Wear, wangi yang pas dan nyaman untuk aktivitas sehari-hari</p> <p>Cara Pakai<br>- Semprot pada titik nadi dengan jarak 15-20 cm<br>- Tunggu hingga kering</p>
A104: 108418 | B104: Blooming Amoure Eau De Parfum | C104: 62fb16f36d42e66ec212086f | D104: 269000 | E104: 4.5789474e+15 | F104: <p>Parfum yang menceritakan mekarnya kisah cinta, dari percikan manis yang segar sampai akhir yang comforting.</p> <p>NOTES<br>TOP: Ginger, Carnation, Green Leaves<br>MID: Tuberose, Jasmine<br>BASE: Musk, Sandalwood</p> <p>Cocok buat kamu yang suka parfum floral musky yang romantic dan soft!</p> <p>- Long-Lasting Scent, tahan lama untuk menemani aktivitasmu<br>- Perfect for Daily Wear, nyaman dipakai untuk aktivitas sehari-hari</p> <p>Cara Pakai<br>- Semprot pada titik nadi dengan jarak 15-20 cm<br>- Tunggu hingga kering</p>
A105: 86995 | B105: Troupe - Extrait De Parfum | C105: 60d4e2c6443396b9504d4beb | D105: 249000 | E105: 4.6289683e+15 | F105: <p>Parfum yang menghadirkan kesan fresh dan graceful, dengan bukaan fruity segar yang bertemu floral lembut dan musky amber.</p> <p>NOTES<br>TOP: Mandarin Orange, Pear<br>MID: Rose, Neroli, Freesia<br>BASE: Patchouli, Musk, Amber</p> <p>Cocok buat kamu yang suka parfum fresh floral yang delicate dan graceful!</p> <p>- Long-Lasting Scent, tahan lama untuk menemani aktivitasmu<br>- Perfect for Daily Wear, wangi yang pas dan nyaman untuk aktivitas sehari-hari</p> <p>Cara Pakai<br>- Semprot pada titik nadi dengan jarak 15-20 cm<br>- Tunggu hingga kering</p>
A106: 117552 | B106: Untitled Aroma 02 | C106: 62c7f51270c7e2af7c6ad720 | D106: 385000 | E106: 4.7358491e+15 | F106: <p>Di kolaborasi kedua antara HMNS dan Maliq &amp; D’Essentials, Untitled Aroma 02 ini, kita ingin mengingatkan sesuatu yang mungkin sering terlupakan. Yakni, betapa cantiknya kamu. <br><br>Dengan Absolute Rose yang lembut, berpadu dengan Musk Milk yang menenangkan. Saat keduanya bertemu, terciptalah wangi yang bukan hanya memikat, tapi juga terasa begitu personal.<br><br>Lalu, ada sentuhan kecil dari Anise yang segar, Violet yang menambahkan kelembutan, Orris yang anggun, dan Cashmere yang menyatukan semuanya dalam harmoni sempurna.<br><br>Ketahanan: 4-5 Jam<br>Jejak Aroma: Sedang hingga kuat<br>Proyeksi: 1,5 - 2 meter<br>Jenis: Eau de Parfum (EDP)<br>Kategori Wangi: Floral Musk</p>
A107: 123180 | B107: Project 1945 Bamboe Roencing Perfume | Extrait de Parfum Unisex | C107: 64bf8ffd47133c15bf961d74 | D107: 345000 | E107: 4.7971014e+15 | F107: <p>Bamboe Roencing adalah cerminan tekad hati, persatuan, dan semangat pantang menyerah.<br>Terinspirasi dari bambu runcing - simbol perjuangan rakyat Indonesia - serta filosofi motif Pucuk Rebung dan anyaman bambu yang melambangkan keteguhan dan kekuatan. Bamboe Roencing hadir bukan hanya sebagai aroma, tapi sebagai pengingat akan semangat kita.<br><br>Perpaduan aroma Bergamot, Osmanthus, dan Musk menciptakan karakter wangi yang menyegarkan dan membangkitkan harapan serta keberanian dalam menghadapi hari yang penuh tantangan.</p>
A108: 121443 | B108: Black Love | C108: 687f0e912e6e4dd7b8ae25dd | D108: 189000 | E108: 4.8730159e+15 | F108: <p>Black Love memadukan aroma kopi, vanilla, dan almond pahit yang misterius dan memikat dalam satu semprotan.</p> <p>NOTES<br>- Coffee<br>- Vanilla<br>- Bitter Almond</p> <p>Cocok buat kamu yang suka parfum coffee gourmand yang dark, warm, dan sensual!</p> <p>- Long-Lasting Scent, tahan lama untuk menemani aktivitasmu<br>- Perfect for Daily Wear, wangi yang pas dan nyaman untuk aktivitas sehari-hari</p> <p>Cara Pakai<br>- Semprot pada titik nadi dengan jarak 15-20 cm<br>- Tunggu hingga kering</p>
A109: 121488 | B109: Cuddle Eau De Parfum | C109: 667d3cc467565050b7424bc9 | D109: 99000 | E109: 4.8869561e+15 | F109: <p>Cuddle Eau De Parfum menghadirkan aroma soft musky yang clean dan comforting.</p> <p>NOTES<br>TOP: Aldehydes, Lily<br>MID: Rose, Iris<br>BASE: Musk, Ambrette</p> <p>Cocok buat kamu yang suka parfum soft musky yang clean, powdery, dan comforting!</p> <p>- Long-Lasting Scent, ketahanan medium to high<br>- Perfect for Daily Wear, wangi yang pas dan nyaman untuk aktivitas sehari-hari</p> <p>Cara Pakai<br>- Semprot pada titik nadi dengan jarak 15-20 cm<br>- Tunggu hingga kering</p>
A110: 107234 | B110: Healing Trail | C110: 6510fae507d9f80342bc6d05 | D110: 299000 | E110: 4.6882142e+16 | F110: <p>Parfum fresh woody yang memberikan rasa tenang dan bebas seperti menyatu dengan alam.</p> <p>NOTES<br>TOP: Ozonic, Citrus, Armoise<br>MID: Water Flowers, Hedione, Woody<br>BASE: Akigalawood, Cedarwood, Sandalwood</p> <p>Cocok buat kamu yang suka parfum fresh dan earthy!</p> <p>- Long-Lasting Scent, tahan lama dengan aroma yang menyegarkan<br>- Nature Inspired Aroma, menghadirkan suasana rileks dan menenangkan<br>- Perfect for Daily Reset, cocok dipakai untuk menemani aktivitas harian</p> <p>Cara Pakai<br>- Semprot pada titik nadi dengan jarak 15-20 cm<br>- Tunggu hingga kering</p>
A111: 122877 | B111: RAE NIRA - Extrait de Parfum | C111: 60d4e2c6443396b9504d4beb | D111: 349000 | E111: 4.8275862e+15 | F111: <p>Parfum yang menyimpan rasa hangat dan akrab, seperti memori lembut yang menenangkan lewat eucalyptus dan balsamic warmth.</p> <p>NOTES<br>TOP: Eucalyptus<br>MID: Immortelle<br>BASE: Tolu Balsam</p> <p>Cocok buat kamu yang suka parfum aromatic balsamic yang warm dan comforting!</p> <p>- Long-Lasting Scent, tahan lama untuk menemani aktivitasmu<br>- Perfect for Daily Wear, wangi yang pas dan nyaman untuk aktivitas sehari-hari</p> <p>Cara Pakai<br>- Semprot pada titik nadi dengan jarak 15-20 cm<br>- Tunggu hingga kering</p>
A112: 122235 | B112: Project 1945 Princess of Java Hair & Body Mist Unisex | HBM 150ml | C112: 64bf8ffd47133c15bf961d74 | D112: 145000 | E112: 4.8148148e+15 | F112: <p>Hair &amp; Body Mist Princess of Java, dari segarnya Pear Hijau, manisnya Tuberose, dan lembutnya Jasmine. Adalah sebuah wewangian mist yang ringan, multifungsi, dan menyegarkan untuk menjadi teman setia kamu!<br><br><br><br>Dilengkapi dengan tambahan formulasi Hydrogenated Castor Oil, Sunflower Seed Oil, dan Jojoba Seed Oil untuk membantu menjaga dan menutrisi rambut serta kulit kamu.</p><p>Fruity, Floral</p>
... A123: 107235 | B123: Madly, Deeply, Loved | C123: 6510fae507d9f80342bc6d05 | D123: 299000 | E123: 4.6458333e+15 | F123: <p>Parfum yang menghadirkan rasa hangat dan dalam seperti dicintai sepenuhnya.</p> <p>NOTES<br>TOP: Grapefruit, Pepper, Cinnamon, Rhubarb<br>MID: Saffron, Rose, Tea, Olibanum<br>BASE: Sandalwood, Patchouli Dust, French Vetiver, Vanilla</p> <p>Cocok buat kamu yang suka parfum spicy floral yang romantis!</p> <p>- Long-Lasting Scent, tahan lama dengan karakter yang elegan<br>- Romantic &amp; Warm Aroma, memberikan kesan hangat dan mendalam<br>- Perfect for Special Moments, cocok dipakai saat momen spesial</p> <p>Cara Pakai<br>- Semprot pada titik nadi dengan jarak 15-20 cm<br>- Tunggu hingga kering</p>
A124: 124742 | B124: Pink Beach 50ml Eau de Parfum | C124: 66fba216e8005543698af0d8 | D124: 199000 | E124: 5.0 | F124: <p>Buah juniper, buket bunga, dan aroma bedak menyeimbangkan wewangian, menciptakan sensasi tenang dan damai dari seprai linen. Bersantai di tempat tidur Anda, membaca buku favorit Anda dengan musik balada lembut yang diputar di latar belakang, dengan sinar matahari keemasan yang hangat menyaring melalui jendela besar, membelai Anda dalam pelukannya yang menenangkan.</p>
A125: 106038 | B125: Galleria Eau de Parfum | C125: 630c79bfa09d276df7478c18 | D125: 199000 | E125: 4.531746e+15 | F125: <p>Parfum yang membawa kamu ke dunia floral yang bebas dan feminin, dengan aroma tuberose, honey, dan plum yang airy serta graceful.</p> <p>NOTES<br>TOP: Cape Jasmine, Plum<br>MIDDLE: Tuberose, Oeillet<br>BASE: Honey, Redwood</p> <p>Cocok buat kamu yang suka parfum sweet floral, romance, dan relaxed.</p> <p>- Long-Lasting Scent, ketahanan 4/5<br>- Perfect for Daily Wear, wangi yang pas dan nyaman untuk aktivitas sehari-hari</p> <p>Cara Pakai<br>- Semprot pada titik nadi dengan jarak 15-20 cm<br>- Tunggu hingga kering</p>
A126: 125571 | B126: O Hyper Bloom Extrait | C126: 62c7f51270c7e2af7c6ad720 | D126: 525000 | E126: 4.75 | F126: <p>-</p>
A127: 126322 | B127: Desert Lumina Extrait De Parfume | C127: 5db51d092023815654e4cc93 | D127: 67500 | E127: 4.8888889e+15 | F127: <p>Scarlett Whitening Extrait De Parfum by world class perfumer, long-lasting up to 16 hours, and perfect for daily-use. <br><br>Luxurious Scent with Affordable Price! <br><br><strong>Scarlett Whitening Extrait de Parfum DESERT LUMINA</strong> <br>Gender - Unisex | Woman <br>Oriental + Ambery + Gourmand <br>Top notes: Amber, Cedarwood <br>Heart Notes: Caramel, Oakmoss <br>Bottom Notes: Vanilla, Tonka</p>
A128: 122357 | B128: Slavina Fine Fragrance Mist Ocean Dream | C128: 67bbeaee630f7e48677f515a | D128: 119000 | E128: 4.8571429e+15 | F128: <p>Aroma tropis yang menyegarkan dengan perpaduan orange dan floral. Berasal dari wangi-wangian alam Wood dan Musk yang menenangkan</p>
A129: 89661 | B129: Spring In New York | C129: 5f5640bc311107db64724988 | D129: 54000 | E129: 4.5473856e+16 | F129: <p>Esens dari musim semi! Kesegaran buah pir yang matang berpadu dengan bunga Freesia yang baru mekar, diseimbangkan oleh Mawar, Amber, Nilam, dan Whitemusk.</p><p>Highlights : </p><p>Halal Certified</p><p>Cruelty Free</p><p>Long Lasting Fragrance</p><p> </p>
A130: 113697 | B130: Cloud Mist - Remedia Amoris | C130: 60d4e2c6443396b9504d4beb | D130: 199000 | E130: 4.5555556e+15 | F130: <p><em>Remedia Amoris mengeksplorasi kerumitan dan pelajaran cinta kedua, di mana hati yang terluka belajar untuk menyembuhkan dan menavigasi kekacauan romantis mereka. Remedia Amoris adalah kaleidoskop emosi, menawarkan refleksi pahit manis tentang kegembiraan dan ilusi yang hancur yang menyertai perjalanan kedua untuk menemukan seseorang yang istimewa.</em></p><p></p><p>CHARACTER : Woody, Aromatic, Green </p><p>Top Notes | Bergamot, Spearmint</p><p>Middle Notes | Kyobancha, Jasmine bud, Sweet violet</p><p>Dry-down Notes | Chantilly cream, Atlas cedar, Cashmeran "</p>
A131: 120399 | B131: Emma Intense | C131: 684fc0d7d4bf7febcf441ede | D131: 129000 | E131: 4.6153846e+15 | F131: <p>Emma terasa seperti sinar matahari yang menyinari buku, menghadirkan aroma woody dari kertas dan nuansa ink yang rich, memberi kesan tenang dan powerful.</p> <p>NOTES<br>- Cardamom, Elemi<br>- Violet Leaves, Incense, Dreamwood<br>- Sandalwood</p> <p>Cocok buat kamu yang suka parfum woody aromatic yang calming, warm, dan sophisticated!</p> <p>- Long-Lasting Scent, tahan lama untuk menemani aktivitasmu<br>- Perfect for Daily Wear, wangi yang pas dan nyaman untuk aktivitas sehari-hari</p> <p>Cara Pakai<br>- Semprot pada titik nadi dengan jarak 15-20 cm<br>- Tunggu hingga kering</p>
A132: 120524 | B132: The Elusive | C132: 6510fae507d9f80342bc6d05 | D132: 299000 | E132: 4.9058608e+15 | F132: <p>Parfum sweet woody yang unik dan misterius.</p> <p>NOTES<br>TOP: Cherry, Raspberry<br>MID: Praline, Heliotrope, Rose<br>BASE: Palo Santo, Tonka Bean, Vanilla</p> <p>Cocok buat kamu yang suka parfum sweet dan mysterious!</p> <p>- Long-Lasting Scent, tahan lama dengan karakter yang kuat<br>- Sweet Woody Aroma, memberikan kesan unik dan elegan<br>- Perfect for Night Wear, cocok dipakai saat malam hari</p> <p>Cara Pakai<br>- Semprot pada titik nadi dengan jarak 15-20 cm<br>- Tunggu hingga kering</p>
A133: 124736 | B133: Pink Drops Extrait de Parfum | C133: 66fba216e8005543698af0d8 | D133: 239000 | E133: 4.6666667e+15 | F133: <p>Pink Drops bukan sekadar parfum, melainkan kenangan masa kecil dalam botol. Bayangkan aroma manis dan lembut stroberi yang direbus dalam susu, wewangian yang langsung membangkitkan kenangan masa kecil. Parfum ini menangkap esensi kenyamanan, jenis kenyamanan yang membawa kembali sore hari yang dihabiskan meringkuk dengan selimut dan secangkir minuman hangat. Manisnya stroberi yang menyenangkan berpadu dengan kehangatan lembut susu, menciptakan aroma yang mengundang sekaligus membangkitkan nostalgia.</p>
A134: 121707 | B134: RAHASIA Dreamy Matcha EDP | C134: 66ed2767c46f3a83999c0374 | D134: 228000 | E134: 4.952381e+16 | F134: <p>Parfum yang menghadirkan aroma matcha creamy dengan sentuhan floral yang playful dan addictive.</p> <p>NOTES<br>TOP: Matcha, Pink Pepper, Mandarin<br>MIDDLE: Jasmine, Tuberose, Orange Flower, Muguet, Raspberry Type: Extrait de Parfum</p> <p>Cocok buat kamu yang suka parfum fresh, fruity, dan matcha gourmand!</p> <p>- Long-Lasting Scent, tahan lama untuk menemani aktivitasmu<br>- Perfect for Daily Wear, wangi yang pas dan nyaman untuk aktivitas sehari-hari</p> <p>Cara Pakai<br>- Semprot pada titik nadi dengan jarak 15-20 cm<br>- Tunggu hingga kering</p>
A135: 98258 | B135: 1970 | C135: 6311def8368f94cfd772b44d | D135: 329000 | E135: 4.7777778e+15 | F135: <p>1970 menghadirkan aroma spices dan woody yang elegan, memadukan sisi maskulin, sedikit manis, dan amber untuk kesan sexy yang cocok dipakai di momen romantis.</p> <p>NOTES<br>TOP: Pink Pepper, Juniper, Violet, Grapefruit<br>MID: Cinnamon, Sage, Vanilla<br>BASE: Amber, Tonka Bean, Toffee, Oak</p> <p>Cocok buat kamu yang suka parfum oriental fougere yang spicy, woody, dan sensual!</p> <p>- Long-Lasting Scent, tahan lama untuk menemani aktivitasmu<br>- Perfect for Daily Wear, wangi yang pas dan nyaman untuk aktivitas sehari-hari</p> <p>Cara Pakai<br>- Semprot pada titik nadi dengan jarak 15-20 cm<br>- Tunggu hingga kering</p>
A136: 108411 | B136: Secretly Sexy Eau De Parfum | C136: 62fb16f36d42e66ec212086f | D136: 269000 | E136: 4.547619e+16 | F136: <p>Parfum yang membawa aura misterius dan feminin, seperti lagu manis yang membuat orang ingin tahu lebih jauh.</p> <p>NOTES<br>TOP: Apple, Orange, Red Berries<br>MID: Rose, Jasmine, Lily<br>BASE: Vanilla, Cedarwood, Sandalwood, Musk</p> <p>Cocok buat kamu yang suka parfum fruity floral yang mysterious dan feminine!</p> <p>- Long-Lasting Scent, tahan lama untuk menemani aktivitasmu<br>- Perfect for Daily Wear, nyaman dipakai untuk aktivitas sehari-hari</p> <p>Cara Pakai<br>- Semprot pada titik nadi dengan jarak 15-20 cm<br>- Tunggu hingga kering</p>
A137: 110657 | B137: French Vanilla EDP | C137: 5f5640bc311107db64724988 | D137: 209000 | E137: 4.6361111e+15 | F137: <p>Parfum yang menghadirkan aroma vanilla lebih intense dan creamy, dengan coconut milk dan raspberry manis seperti es krim di Paris.</p> <p>NOTES:<br>- Vanilla<br>- Coconut Milk<br>- Raspberry</p> <p>Cocok buat kamu yang suka parfum sweet, creamy, dan fruity!</p> <p>- Long-Lasting Scent, tahan lama untuk menemani aktivitasmu<br>- Perfect for Daily Wear, wangi yang pas dan nyaman untuk aktivitas sehari-hari</p> <p>Cara Pakai<br>- Semprot pada titik nadi dengan jarak 15-20 cm<br>- Tunggu hingga kering</p>
A138: 117714 | B138: CARESO Eau De Toilette French Vanilla | C138: 5f5640bc311107db64724988 | D138: 82000 | E138: 4825 | F138: <p><em>Ready for a mesmerising vanilla? Think creamy coconut milk, sweet raspberry with a touch of vanilla. Inspired by the Parisian ice cream parlour, French Vanilla is creamy, indulgent, faintly floral with a hint of berry goodness, and in a word: delicious!<br>The perfume will last upto 6 hours.</em></p>
A139: 122052 | B139: First Kiss | C139: 687f0e912e6e4dd7b8ae25dd | D139: 349000 | E139: 4.796748e+15 | F139: <p>First Kiss menghadirkan aroma segar yang terasa seperti pagi cerah dan momen santai dengan secangkir teh hangat.</p> <p>NOTES<br>- Fresh Tea Accord<br>- Soft Floral<br>- Clean Musk</p> <p>Cocok buat kamu yang suka parfum fresh clean yang soft dan comforting!</p> <p>- Long-Lasting Scent, tahan lama untuk menemani aktivitasmu<br>- Perfect for Daily Wear, wangi yang pas dan nyaman untuk aktivitas sehari-hari</p> <p>Cara Pakai<br>- Semprot pada titik nadi dengan jarak 15-20 cm<br>- Tunggu hingga kering</p>
A140: 114573 | B140: Rahasia Single Glow | C140: 66ed2767c46f3a83999c0374 | D140: 186480 | E140: 4.6190476e+16 | F140: <p>Parfum yang menemani kamu untuk glow up dan menikmati hidup dengan aroma citrus fruity floral yang cheerful.</p> <p>NOTES<br>TOP: Bergamot, Pear, Mango<br>MIDDLE: Peony, Rose<br>BASE: Musk, Dry Amber, Raspberry </p> <p>Cocok buat kamu yang suka parfum fresh, warm, dan musky!</p> <p>- Long-Lasting Scent, tahan hingga 10–12 jam<br>- Perfect for Daily Wear, wangi yang pas dan nyaman untuk aktivitas sehari-hari</p> <p>Cara Pakai<br>- Semprot pada titik nadi dengan jarak 15-20 cm<br>- Tunggu hingga kering</p>
A141: 108425 | B141: Soul Signature Eau De Parfum | C141: 62fb16f36d42e66ec212086f | D141: 269000 | E141: 468421052631579 | F141: <p>Parfum yang merayakan proses mengenal diri sendiri, terasa hangat, optimis, dan timeless.</p> <p>NOTES<br>TOP: Bergamot, Tangerine, Pear Accord<br>MID: Neroli, Neroli Bud, Orange Blossom, Sambac Jasmine<br>BASE: Amber Accord, Benzoin, Bourbon Vanilla, White Musk Accord</p> <p>Cocok buat kamu yang suka parfum citrus floral yang warm dan comforting!</p> <p>- Long-Lasting Scent, tahan lama untuk menemani aktivitasmu<br>- Perfect for Daily Wear, nyaman dipakai untuk aktivitas sehari-hari</p> <p>Cara Pakai<br>- Semprot pada titik nadi dengan jarak 15-20 cm<br>- Tunggu hingga kering</p>
A142: 122358 | B142: Slavina Fine Fragrance Mist Love Journey | C142: 67bbeaee630f7e48677f515a | D142: 119000 | E142: 4.7777778e+15 | F142: <p>Aroma floral bernuansa lembut dan elegan dari bunga Lily dan Jasmine dengan sentuhan Woody dari Rosewood. Pepaduan Orange dan Cherry memberikan kesegaran serta sentuhan manis yang feminim.</p>
A143: 120396 | B143: Edith Intense | C143: 684fc0d7d4bf7febcf441ede | D143: 129000 | E143: 4.7555556e+16 | F143: <p>Edith hadir seperti denting halus kalung kucing berlian yang bergema di tangga marmer, aromanya terasa elegan bahkan sebelum terlihat.</p> <p>NOTES<br>- Bergamot<br>- Saffron, Rose<br>- Amber, Honey, Sandalwood</p> <p>Cocok buat kamu yang suka parfum elegan dengan sentuhan spicy, floral, dan warm woody!</p> <p>- Long-Lasting Scent, tahan lama untuk menemani aktivitasmu<br>- Perfect for Daily Wear, wangi yang pas dan nyaman untuk aktivitas sehari-hari</p> <p>Cara Pakai<br>- Semprot pada titik nadi dengan jarak 15-20 cm<br>- Tunggu hingga kering</p>
A144: 117715 | B144: CARESO Eau De Toilette Jasmine Blossoms | C144: 5f5640bc311107db64724988 | D144: 82000 | E144: 4.75 | F144: <p><em>Extracted from the finest arabian Jasmine petals, we formulated a fragrance that gives off an elegance yet feminine feel.<br>The perfume will last upto 6 hours.</em></p>
A145: 123701 | B145: Eau de Parfum - Golden Lumière | C145: 62bbfd4abd4201d78fc0e8f5 | D145: 115000 | E145: 2273727 | F145: <p>Golden Lumière menghadirkan tuberose yang mekar keemasan, berkilau dengan sentuhan petitgrain, lalu menetap hangat dalam aroma sandalwood yang feminin dan sensual.</p> <p>NOTES<br>TOP: Tuberose, Petitgrain<br>MID: Rose, Jasmine, Orange Flower<br>BASE: Lactones, Musky, Sandalwood</p> <p>Cocok buat kamu yang suka parfum white floral yang warm, sensual, dan elegan!</p> <p>- Long-Lasting Scent, tahan lama untuk menemani aktivitasmu<br>- Perfect for Daily Wear, wangi yang pas dan nyaman untuk aktivitas sehari-hari</p> <p>Cara Pakai<br>- Semprot pada titik nadi dengan jarak 15-20 cm<br>- Tunggu hingga kering</p>
A146: 121446 | B146: Deep Mountain | C146: 687f0e912e6e4dd7b8ae25dd | D146: 189000 | E146: 4.8958333e+15 | F146: <p>Deep Mountain diciptakan untuk jiwa petualang yang mencintai alam terbuka, menghadirkan aroma segar dan earthy yang menenangkan.</p> <p>NOTES<br>- Fresh Air Accord<br>- Woody Notes<br>- Earthy Musk</p> <p>Cocok buat kamu yang suka parfum woody fresh yang earthy dan adventurous!</p> <p>- Long-Lasting Scent, tahan lama untuk menemani aktivitasmu<br>- Perfect for Daily Wear, wangi yang pas dan nyaman untuk aktivitas sehari-hari</p> <p>Cara Pakai<br>- Semprot pada titik nadi dengan jarak 15-20 cm<br>- Tunggu hingga kering</p>
A147: 108416 | B147: Siren Eau De Parfum | C147: 62fb16f36d42e66ec212086f | D147: 269000 | E147: 465625 | F147: <p>Parfum yang menghadirkan kontradiksi penuh kejutan, dari sisi manis yang playful sampai kesan sensual yang menarik atensi.</p> <p>NOTES<br>TOP: Pear, Red Fruit, Bergamot, Pink Pepper<br>MID: Jasmine, Orris, Magnolia, Red Rose, Orange Blossom<br>BASE: Amber, Caramel, Vetiver, Vanilla</p> <p>Cocok buat kamu yang suka parfum fruity floral yang sensual dan playful!</p> <p>- Long-Lasting Scent, tahan lama untuk menemani aktivitasmu<br>- Perfect for Daily Wear, nyaman dipakai untuk aktivitas sehari-hari</p> <p>Cara Pakai<br>- Semprot pada titik nadi dengan jarak 15-20 cm<br>- Tunggu hingga kering</p>
A148: 127390 | B148: Utopia Extrait de Parfum | C148: 66fba216e8005543698af0d8 | D148: 459000 | E148: 4.7619048e+15 | F148: <p>Utopia, terinspirasi oleh konsep dunia yang sempurna, adalah wewangian yang dibuat dengan cermat yang mewujudkan esensi taman bunga putih yang ideal. <br><br>Diawali dengan pelukan bergamot Calabria yang mempesona dan semburan kesegaran jeruk, wewangian ini dengan mulus bertransisi menjadi perpaduan lembut Ylang-ylang dan melati sambac, diperkaya dengan sentuhan elegan iris dan aroma air yang menyegarkan. Wewangian ini diakhiri dengan nada dasar kayu dan musk putih yang manis, menciptakan aura yang canggih dan menenangkan.</p>
A149: 110659 | B149: Velvet Rose EDP | C149: 5f5640bc311107db64724988 | D149: 209000 | E149: 4.5824561e+15 | F149: <p>Parfum yang menangkap aroma musim semi di Paris lewat rose dan bergamot yang feminin serta memorable.</p> <p>NOTES:<br>- Rose<br>- Bergamot</p> <p>Cocok buat kamu yang suka parfum floral dan fresh!</p> <p>- Long-Lasting Scent, tahan lama untuk menemani aktivitasmu<br>- Perfect for Daily Wear, wangi yang pas dan nyaman untuk aktivitas sehari-hari</p> <p>Cara Pakai<br>- Semprot pada titik nadi dengan jarak 15-20 cm<br>- Tunggu hingga kering</p>
A150: 114822 | B150: Mykonos Musk Aura | C150: 66fba216e8005543698af0d8 | D150: 299000 | E150: 4.6097222e+15 | F150: <p>Parfum yang menghadirkan aura musky yang clean dengan sentuhan citrus, apple, dan floral notes.</p> <p>NOTES<br>TOP: Bergamot, Yuzu, Apple<br>MIDDLE: Lily of the Valley, Sambac Jasmine, Ylang-Ylang<br>BASE: Amber, Musk, Citrus, Nectarine</p> <p>Cocok buat kamu yang suka parfum fresh, fruity, dan warm!</p> <p>- Long-Lasting Scent, tahan lama untuk menemani aktivitasmu<br>- Perfect for Daily Wear, wangi yang pas dan nyaman untuk aktivitas sehari-hari</p> <p>Cara Pakai<br>- Semprot pada titik nadi dengan jarak 15-20 cm<br>- Tunggu hingga kering</p>
A151: 123781 | B151: WonderPerfume! EDP Hair & Body Mist | C151: 5d3ac307a6992471b7c97b2f | D151: 169000 | E151: 4.6666667e+15 | F151: <p>Menghadirkan aroma lembut yang segar dan tahan hingga 8 jam<br><br>Mengandung:<br>Honey (Madu): Menguatkan folikel rambut dan mengembalikan kilau alami rambut.<br>Argan Oil (Minyak Argan): Mengurangi kerontokan, merangsang pertumbuhan rambut sehat, dan memberikan efek melembapkan mendalam.<br>Hyaluronic Acid (Asam Hialuronat): Menyegarkan rambut kering dan kusam serta membantu mengurangi rambut mengembang.<br>Anti-UV Agent: Melindungi rambut dari kerusakan akibat sinar UV.<br>Anti-Pollution Agent: Melindungi rambut dari paparan polusi udara.<br>Heat Protectant Agent: Melindungi rambut dari kerusakan akibat alat penata rambut bersuhu tinggi.<br><br>Cocok untuk semua jenis rambut.<br>Dapat digunakan pada tubuh, kain, dan barang pribadi lainnya.<br><br>Bebas bahan berbahaya: tidak mengandung Paraben, Kamper, Mentol, Sulfat, maupun Fenol.<br>Tidak diuji pada hewan (Cruelty-free)<br>Vegan<br>Halal<br><br>Netto: 100 ml<br><br>Nomor BPOM:<br>Neroli + Iris: NA18241002069<br>Rose + Honey: NA18250608881<br>Gardenia + Ylang Ylang: NA18250608969<br>Vanilla + Sandalwood: NA18250608967<br>Lily + Bergamot: NA18250608971<br>Camellia + Apple: NA18250608970</p>
A152: 114873 | B152: Mykonos Affair 15 | C152: 66fba216e8005543698af0d8 | D152: 99000 | E152: 4.6904762e+15 | F152: <p>Parfum dengan aroma raspberry sorbet yang manis dan playful untuk kesan ceria yang memikat.</p> <p>NOTES<br>TOP: Raspberry Sorbet<br>MIDDLE: -<br>BASE: -</p> <p>Cocok buat kamu yang suka parfum fruity!</p> <p>- Long-Lasting Scent, tahan lama untuk menemani aktivitasmu<br>- Perfect for Daily Wear, wangi yang pas dan nyaman untuk aktivitas sehari-hari</p> <p>Cara Pakai<br>- Semprot pada titik nadi dengan jarak 15-20 cm<br>- Tunggu hingga kering</p>
A153: 120518 | B153: The Fearless | C153: 6510fae507d9f80342bc6d05 | D153: 299000 | E153: 4.9302744e+15 | F153: <p>Parfum dengan aroma bold dan hangat yang memancarkan keberanian dan rasa percaya diri.</p> <p>NOTES<br>TOP: Cognac<br>MID: Tonka, Oat, Cinnamon<br>BASE: Sandalwood, Vanilla, Praline, Woody Ambery</p> <p>Cocok buat kamu yang suka parfum warm, spicy, dan elegan!</p> <p>- Long-Lasting Scent, tahan lama untuk menemani aktivitas seharian<br>- Warm &amp; Bold Aroma, memberikan kesan percaya diri dan berani<br>- Comfortable for Daily Wear, tetap nyaman dipakai kapan saja</p> <p>Cara Pakai<br>- Semprot pada titik nadi dengan jarak 15-20 cm<br>- Tunggu hingga kering</p>
A154: 124127 | B154: Haven Retreat Eau De Parfum | C154: 69292226555238423bb4eecf | D154: 295000 | E154: 4.952381e+16 | F154: <p>Eau de parfum dengan rice accord, clary sage, amber, dan musk yang bantu suasana terasa comforting, relaxing, dan cozy seperti retreat di rumah.</p> <p>Cocok buat kamu yang ingin wangi comforting untuk me-time dan melepas worries.</p> <p>- Comforting Scent, memberi rasa comfort dan relaxation<br>- Home Sanctuary Inspiration, dengan sensasi seperti retreat ke tempat paling nyaman<br>- Mood Uplift Care, cocok untuk momen me-time agar mood terasa lebih baik<br>- Grounding Ritual, menciptakan rasa lebih grounded dan tenang<br>- Consumer Tested, teruji berdasarkan satisfaction test pada 40 orang</p> <p>Fragrance Notes<br>- Top Notes: Pepper, Bergamot, Clary Sage Oil<br>- Middle Notes: Mimosa Absolute, Rice Accord, Lily of the Valley<br>- Base Notes: Cedarwood, Amber, Musk, Sulawesi Patchouli</p> <p>Cara Pakai<br>- Semprotkan dari jarak 15–20 cm pada titik nadi</p>
A155: 113440 | B155: In the Library | C155: 6510fae507d9f80342bc6d05 | D155: 299000 | E155: 4.8233618e+15 | F155: <p>Parfum woody aromatic yang menghadirkan suasana hangat dan menenangkan seperti berada di perpustakaan.</p> <p>NOTES<br>TOP: Pencil Accord<br>MID: Violet Flower, Pink Pepper, Cedarwood Heart Virginia<br>BASE: Patchouli, Sandalwood, Amber Woody, Ambertonic</p> <p>Cocok buat kamu yang suka parfum woody dan unik!</p> <p>- Long-Lasting Scent, tahan lama dengan karakter yang khas<br>- Cozy &amp; Intellectual Aroma, menghadirkan kesan hangat dan tenang<br>- Unique Pencil Accord, memberikan aroma unik yang memorable</p> <p>Cara Pakai<br>- Semprot pada titik nadi dengan jarak 15-20 cm<br>- Tunggu hingga kering</p>
A156: 117717 | B156: CARESO Eau De Toilette Velvet Rose | C156: 5f5640bc311107db64724988 | D156: 82000 | E156: 4.617284e+15 | F156: <p><em>The memory of a spring date in Paris. To get to Versailles, one needed to cross through a natural grove of wild roses. The moments in Paris, brought home an unforgettable memory of a unique combinations of smells that held the memories of the trip.<br>The perfume will last upto 6 hours.</em></p>
... A161: 114863 | B161: Mykonos Tea Poetry | C161: 66fba216e8005543698af0d8 | D161: 99000 | E161: 46146 | F161: <p>Parfum yang menghadirkan puisi aroma teh dengan sentuhan floral, candied fruit, honey, dan smoked black tea.</p> <p>NOTES<br>TOP: Rose, Jasmine, Ylang-Ylang<br>MIDDLE: Candied Fruit, Balsam, Orange Flower, Pepper, Smoked Black Tea<br>BASE: Honey, Smoked Black Tea, Cedarwood</p> <p>Cocok buat kamu yang suka parfum tea scent dan woody!</p> <p>- Long-Lasting Scent, tahan lama untuk menemani aktivitasmu<br>- Perfect for Daily Wear, wangi yang pas dan nyaman untuk aktivitas sehari-hari</p> <p>Cara Pakai<br>- Semprot pada titik nadi dengan jarak 15-20 cm<br>- Tunggu hingga kering</p>
A162: 127898 | B162: POSTOJNA - Extrait de Parfum | C162: 60d4e2c6443396b9504d4beb | D162: 349000 | E162: 5.0 | F162: <p>Di ambang waktu, apel biru bersarang di tanaman merambat yang menjalar di dinding kuno POSTOJNA saat cahaya indigo senja meresap ke dalam. Muguet bergerak dalam garis-garis murni dan ringan sementara rockrose menyatu dalam kedalaman yang diselimuti cahaya pertama, sebuah keajaiban yang tergantung di antara mitos dan pagi bagi mereka yang menapaki jalan yang belum terjamah.</p>
A163: 120301 | B163: BLP Everyday - Light EDP | C163: 5d3ac307a6992471b7c97a2d | D163: 289000 | E163: 4.7619048e+15 | F163: <p>Create new beginnings everyday and be radiant with BLP EVERYDAY LIGHT <br><br>BLP EVERYDAY is a series of scents defined by the wearer – you! – to elevate your everyday ritual and speak volume of your confidence, elegance, freshness, and warmth. <br><br>Imagine waking up in your dream place. The light comes in softly, and a refreshing scent of bergamot paired with cherry enters. Feel the breeze filled with cyclamen, cashmere wood, and lily-of-the-valley. Then put on a clean, crisp shirt reminiscent of woody patchouli and sandalwood. Your spirit sweetly lingers like iris. <br><br>TOP <br>Bergamot, Cherry <br><br>HEART <br>Cyclamen, Cashmere wood, Lily-of-the-Valley <br><br>BASE <br>Iris, Patchouli, Sandalwood, Musk <br><br>SCENT CHARACTER <br>Soft | Floral | Clean <br></p>
A164: 125572 | B164: EOS Hyper Nova Extrait | C164: 62c7f51270c7e2af7c6ad720 | D164: 525000 | E164: 4.7777778e+15 | F164: <p>-</p>
A165: 108427 | B165: Zen Garden Eau De Parfum | C165: 62fb16f36d42e66ec212086f | D165: 269000 | E165: 4.5353535e+16 | F165: <p>Parfum yang menghadirkan rasa tenang seperti oasis damai, lembut, floral, dan comforting.</p> <p>NOTES<br>TOP: Neroli<br>MID: Rose, Honeysuckle<br>BASE: Magnolia, Jasmine</p> <p>Cocok buat kamu yang suka parfum floral citrus yang calming dan graceful!</p> <p>- Long-Lasting Scent, tahan lama untuk menemani aktivitasmu<br>- Perfect for Daily Wear, nyaman dipakai untuk aktivitas sehari-hari</p> <p>Cara Pakai<br>- Semprot pada titik nadi dengan jarak 15-20 cm<br>- Tunggu hingga kering</p>
A166: 113696 | B166: Cloud Mist - Sonnet 116 | C166: 60d4e2c6443396b9504d4beb | D166: 199000 | E166: 4.6727273e+15 | F166: <p><em>Sonnet 116 mengajak Anda untuk menyelami simfoni penemuan diri dan evolusi—narasi yang dipintal dengan kebijaksanaan cinta diri, di mana jiwa akhirnya menemukan ritme harmonis mereka dan merangkul cinta tanpa syarat. Soneta ini membebaskan hati dan pikiran melalui hasrat, kepercayaan, dan pelukan bersama yang terasa tepat.</em></p><p></p><p>CHARACTER : Floral, Gourmand, Woody </p><p>Top Notes | Virgin mojito, Rice powder</p><p>Middle Notes | Fukamushicha, Jasmine Sambac, Cyclamen </p><p>Dry-down Notes | Milk mousse, Sandalwood, Ambrette"</p>
A167: 110541 | B167: Unpatched | C167: 62c7f51270c7e2af7c6ad720 | D167: 398000 | E167: 4.7469136e+15 | F167: <p>Kamu memulai perjalanan di sebuah taman yang dipenuhi Jasmine Sambac, setiap kelopaknya menyimpan keindahan. Aroma Vanilla Madagascar &amp; Chocolate yang gurih mulai menyapa. <br>Kamu berjalan melalui taman yang dikelilingi Rose yang megah. Di antara bunga-bunga ini, kamu merasakan kehangatan Caramel, seolah-olah sinar matahari menyinari kamu. Perjalananmu berlanjut, membawamu ke kedalaman taman yang semakin memikat. Di sini, aroma Tonka Bean Brazil mulai memberikan sentuhan yang lebih mendalam. Lalu, Amber menyelimuti lingkungan sekitar dengan kehangatan yang elegan dan menenangkan, seolah-olah menawarkan pelukan hangat. Akhirnya, Musk menutup perjalananmu dengan lembut.<br><br>Unpatched bertipe Woody Green Leathery. Setiap lapisan aromanya membawamu lebih dekat ke kekuatan dari kayu dan kulit yang tua. This is like opening a door to a world where you are the giver of warmth to every soul.<br>Type: Eau De Parfum - Woody Green Leathery<br>Projection: 1.5 - 2 meters<br>Longevity: 6 hours<br>Sillages Medium</p>
A168: 119347 | B168: Aquaterrae Extrait de Parfum | C168: 657ad93e28f41e975c8a966c | D168: 350000 | E168: 4.9166667e+15 | F168: <p>Kahf Oracle Series Extrait de Parfum 50 ml merupakan New Series dari Kahf Fragrance yang membawakan inspirasi bagi pria untuk selalu menjadi pengingat tentang sosok yang mereka aspirasikan, dan nilai-nilai yang dibutuhkan untuk mencapai tujuan tersebut dengan menggabungkan Captive technology dan Essential oils untuk menciptakan fragrance yang bold, berbeda, aroma yang sangat baru, dan susah untuk ditiru.<br>TOP<br>Grapefruit<br>Pink Pepper<br>Betahydrane<br>Ozonic<br>MIDDLE<br>Geranium<br>Mugane<br>Sage<br>Lavender<br>BOTTOM<br>Lorenox<br>Amber<br>Incense</p>
A169: 110658 | B169: Jasmine Blossom EDP | C169: 5f5640bc311107db64724988 | D169: 209000 | E169: 4.7194719e+16 | F169: <p>Parfum yang menghadirkan racikan jasmine arab yang lebih intense, floral, fresh, dan feminin.</p> <p>NOTES:<br>- Jasmine<br>- Rose<br>- Bergamot<br>- Orange<br>- Lemon<br>- Cashmere</p> <p>Cocok buat kamu yang suka parfum floral, fresh, dan soft!</p> <p>- Long-Lasting Scent, tahan hingga 8 jam<br>- Perfect for Daily Wear, wangi yang pas dan nyaman untuk aktivitas sehari-hari</p> <p>Cara Pakai<br>- Semprot pada titik nadi dengan jarak 15-20 cm<br>- Tunggu hingga kering</p>
A170: 124376 | B170: Mabel Intense | C170: 684fc0d7d4bf7febcf441ede | D170: 129000 | E170: 4.6666667e+15 | F170: <p>Mabel membuka aroma dengan manisnya peach dan apricot yang lembut namun radiant, seperti topaz yang berkilau dalam cahaya.</p> <p>NOTES<br>TOP: Peach, Apricot<br>MID: Osmanthus, Lily of the Valley, Magnolia<br>BASE: Musk, Ambergris</p> <p>Cocok buat kamu yang suka parfum fruity floral yang warm, intimate, dan elegan!</p> <p>- Long-Lasting Scent, tahan lama untuk menemani aktivitasmu<br>- Perfect for Daily Wear, wangi yang pas dan nyaman untuk aktivitas sehari-hari</p> <p>Cara Pakai<br>- Semprot pada titik nadi dengan jarak 15-20 cm<br>- Tunggu hingga kering</p>
A171: 125297 | B171: RSVP - Nevernot Signature Series EDP | C171: 6979dfc48d450be00450df29 | D171: 189000 | E171: 5.0 | F171: <p>Parfum yang rasanya seperti jadi main character di Emily in Paris, dengan aroma fruity manis yang playful seperti milkshake dengan cherry di atasnya.</p> <p>NOTES<br>TOP: Raspberry, Cherry, Peach<br>MIDDLE: Marshmallow, Gardenia, Orchid<br>BASE: Musk, Oak, Ylang-Ylang </p> <p>Cocok buat kamu yang suka parfum intimate dan sweet!</p> <p>- Long-Lasting Scent, tahan hingga 6 jam<br>- Perfect for Daily Wear, wangi yang pas dan nyaman untuk aktivitas sehari-hari</p> <p>Cara Pakai<br>- Semprot pada titik nadi dengan jarak 15-20 cm<br>- Tunggu hingga kering</p>
A172: 122355 | B172: Slavina Fine Fragrance Endless Blossom | C172: 67bbeaee630f7e48677f515a | D172: 119000 | E172: 5.0 | F172: <p>Sentuhan floral yang harum, perpaduan Lavender dan Magnolia yang menyegarkan, dipadukan dengan sentuhan Vanilla dan Sandalwood yang menenangkan.</p>
A173: 114572 | B173: Rahasia Goddess Water | C173: 66ed2767c46f3a83999c0374 | D173: 205305 | E173: 4.5797101e+15 | F173: <p>Parfum yang menghadirkan aura percaya diri dan inner glow lewat sentuhan fruity floral yang warm dan uplifting.</p> <p>NOTES<br>TOP: Pear, Mandarin, Pineapple<br>MIDDLE: Magnolia, Muguet, White Floral<br>BASE: Amber, Sandalwood, Vanilla </p> <p>Cocok buat kamu yang suka parfum fresh dan sweet!</p> <p>- Long-Lasting Scent, tahan hingga 10–12 jam<br>- Perfect for Daily Wear, wangi yang pas dan nyaman untuk aktivitas sehari-hari</p> <p>Cara Pakai<br>- Semprot pada titik nadi dengan jarak 15-20 cm<br>- Tunggu hingga kering</p>
A174: 124167 | B174: Olgaline | C174: 69200f1ca1ea6f13126c7ba9 | D174: 229900 | E174: 4.9047619e+15 | F174: <p>Parfum yang menghadirkan perpaduan rose, woody, dan vanilla yang soft, feminine, dan elegant.</p> <p>Cocok buat kamu yang anggun, smart, tapi tetap easy going!</p> <p>- Long-Lasting Scent, tahan lama untuk menemani aktivitasmu<br>- Perfect for Daily Wear, wangi yang pas dan nyaman untuk aktivitas sehari-hari</p> <p>Cara Pakai<br>- Semprot pada titik nadi dengan jarak 15-20 cm<br>- Tunggu hingga kering</p>
A175: 109671 | B175: Forbidden Garden extrait de Parfume | C175: 658a8e243cca26bc8b2f676b | D175: 249000 | E175: 462962962962963 | F175: <p>Forbidden Garden menggambarkan sosok yang berkuasa, penuh lapisan, dan selalu berhasil mencuri rasa penasaran.</p> <p>NOTES<br>TOP: Green Apple, Rose, Blackberry, Geranium, Violet<br>MID: Jasmine Sambac, Ylang-Ylang, Orris, Raspberry, Red Apple<br>BASE: Musk, Patchouli, Sandalwood, Vanilla, Vetiver</p> <p>Cocok buat kamu yang suka parfum dengan karakter scent floral, fruity, elegant, sweet, sensual!</p> <p>- Long-Lasting Scent, tahan lama untuk menemani aktivitasmu<br>- Perfect for Daily Wear, wangi yang pas dan nyaman untuk aktivitas sehari-hari</p> <p>Cara Pakai<br>- Semprot pada titik nadi dengan jarak 15-20 cm<br>- Tunggu hingga kering</p>
A176: 117777 | B176: Moroccan Sunset | C176: 678f22b3bf9a94d16f30d103 | D176: 229000 | E176: 474712643678161 | F176: <p>Parfum floral gourmand yang menggambarkan sunset eksotis di Maroko yang hangat dan memikat.</p> <p>NOTES<br>TOP: Neroli, Bergamot, Red Fruits<br>MID: Orange Blossom, Jasmine, Cinnamon, Resin<br>BASE: Vanilla, Caramel, Musk, Cedarwood</p> <p>Cocok buat kamu yang suka parfum fruity floral dengan karakter manis, segar, dan feminin!</p> <p>- Long-Lasting Scent, tahan lama untuk menemani aktivitasmu<br>- Fresh Fruity Floral Aroma, memberikan kesan ceria dan menarik<br>- Perfect for Evening &amp; Formal Occasion, cocok dipakai saat malam hari atau acara formal</p> <p>Cara Pakai<br>- Semprot pada titik nadi dengan jarak 15-20 cm<br>- Tunggu hingga kering</p>
A177: 122160 | B177: BARBIE Calabria Peach EDP | C177: 689c00257493d86323be7038 | D177: 299000 | E177: 5.0 | F177: <p>Parfum fruity chypre yang menghadirkan aroma peach manis, playful, dan feminin dengan sentuhan floral yang elegan.</p> <p>NOTES<br>TOP: Bergamot, Peach Skin<br>MIDDLE: Strawberry Jam, Jasmine, White Flowers<br>BASE: Chypre Accord</p> <p>Cocok buat kamu yang suka parfum fruity floral dengan karakter manis, ceria, dan feminin!</p> <p>- Long-Lasting Scent, tahan lama untuk menemani aktivitasmu<br>- Sweet Fruity Floral Aroma, memberikan kesan playful, fresh, dan menarik<br>- Perfect for Daily Wear, nyaman dipakai untuk menemani aktivitas harian</p> <p>Cara Pakai<br>- Semprotkan di urat nadi tangan, area leher belakang, dan belakang telinga<br>- Spray ke baju dengan jarak 15-20 cm</p>
A178: 125301 | B178: Ubud Sanctuary - Nevernot Chapter II: Ubud and 3am series EDP | C178: 6979dfc48d450be00450df29 | D178: 189000 | E178: 5.0 | F178: <p>Parfum yang menghadirkan aroma jasmine lotus yang calming, seperti momen relaksasi setelah hari yang panjang.</p> <p>NOTES<br>TOP: Bergamot, Orange Flower, Galbanum, Clove<br>MIDDLE: Tuberose, Jasmine, Ozonic, Ylang-Ylang<br>BASE: Musk, Amber, Cedarwood, Vanilla</p> <p>Cocok buat kamu yang suka parfum floral, sweet, dan woody!</p> <p>- Long-Lasting Scent, tahan lama untuk menemani aktivitasmu<br>- Perfect for Daily Wear, wangi yang pas dan nyaman untuk aktivitas sehari-hari</p> <p>Cara Pakai<br>- Semprot pada titik nadi dengan jarak 15-20 cm<br>- Tunggu hingga kering</p>
A179: 123592 | B179: Hug Eau de Parfum | C179: 667d3cc467565050b7424bc9 | D179: 99000 | E179: 4.9333333e+15 | F179: <p>NOTES:<br>Top Notes : Orange Blossom, Osmanthus<br>Midde Notes : Amber, Vanilla<br>Base Notes : Vetiver, Precious Wood, Musk<br><br>Longevity: medium to high<br>Sillage: medium<br>Projection: medium</p>
A180: 89662 | B180: French Linen | C180: 5f5640bc311107db64724988 | D180: 54000 | E180: 4.462888e+15 | F180: <p>&nbsp;<br>Memori bermales-malesan di hari Minggu pagi di tempat tidur. Sensasi halus dari linen yang baru dicuci di kulit Anda, memadukan Violet murni dan Hyacinth yang menenangkan. Diseimbangkan dengan bunga putih dan Ylang-Ylang.<br>---------------------------<br>The memory of lingering Sunday mornings in bed. A delicate sensation of freshly washed linen on your skin, mixing together pure Violet and comforting Hyacinth. Balanced with powdery white florals and Ylang-Ylang. </p>
A181: 124169 | B181: O'real | C181: 69200f1ca1ea6f13126c7ba9 | D181: 249900 | E181: 4.8888889e+15 | F181: <p>Parfum yang menghadirkan aroma vanilla yang sexy seductive dengan aura feminine dan classy.</p> <p>Cocok buat kamu yang suka tampil elegan dan percaya diri!</p> <p>- Long-Lasting Scent, tahan lama untuk menemani aktivitasmu<br>- Perfect for Daily Wear, wangi yang pas dan nyaman untuk aktivitas sehari-hari</p> <p>Cara Pakai<br>- Semprot pada titik nadi dengan jarak 15-20 cm<br>- Tunggu hingga kering</p>
A182: 120397 | B182: Alice Intense | C182: 684fc0d7d4bf7febcf441ede | D182: 129000 | E182: 4.7777778e+15 | F182: <p>Alice hadir seperti peri hutan yang menyukai alam dan petualangan. Dalam balutan gaun putih yang mengalir, ia menikmati suasana rainforest dan semilir angin, tenggelam dalam dunianya sendiri.</p> <p>NOTES<br>- Tomato Leaf, Lychee<br>- Geranium, Rose, Red Tomato<br>- Woody Notes</p> <p>Cocok buat kamu yang suka parfum green, fruity, dan woody yang terasa segar!</p> <p>- Long-Lasting Scent, tahan lama untuk menemani aktivitasmu<br>- Perfect for Daily Wear, wangi yang pas dan nyaman untuk aktivitas sehari-hari</p> <p>Cara Pakai<br>- Semprot pada titik nadi dengan jarak 15-20 cm<br>- Tunggu hingga kering</p>
A183: 120298 | B183: BLP Everyday - Hug EDP | C183: 5d3ac307a6992471b7c97a2d | D183: 289000 | E183: 4.8405797e+15 | F183: <p>Have your small moments everyday and be warm with BLP EVERYDAY HUG <br><br>BLP EVERYDAY is a series of scents defined by the wearer – you! – to elevate your everyday ritual and speak volume of your confidence, elegance, freshness, and warmth. <br><br><br>A gentle hug of vanilla and cacao envelops you like your favorite blanket. It brings a recollection of your best memories with a warm feeling. Get yourself a glass of milk and think of one place that gives you a sense of familiarity – like tuberose and jasmine. The feeling’s warm, the mood’s comfortable. <br><br>TOP <br>Milk, Ambrette, Mystikal <br><br>HEART <br>Tuberose, Mahonial, Jasmine, Incense <br><br>BASE <br>Vanilla, Musk, Tonka Bean, Cacao <br><br>SCENT CHARACTER <br>Gourmand | Woody | Oriental <br></p>
A184: 125299 | B184: Kenangan Tea Blend - Nevernot Kenangan EDP | C184: 6979dfc48d450be00450df29 | D184: 189000 | E184: 4.7333333e+15 | F184: <p>Parfum dari kolaborasi Nevernot x Kopi Kenangan ini menghadirkan aroma teh yang segar dan adem, seperti sore damai tanpa notifikasi grup kantor.</p> <p>NOTES<br>TOP: Earl Grey, Bergamot<br>MIDDLE: Jasmine, Geranium<br>BASE: Sandalwood, Musk, Pepper</p> <p>Cocok buat kamu yang suka parfum tea scent, floral, dan woody!</p> <p>- Long-Lasting Scent, tahan lama untuk menemani aktivitasmu<br>- Perfect for Daily Wear, wangi yang pas dan nyaman untuk aktivitas sehari-hari</p> <p>Cara Pakai<br>- Semprot pada titik nadi dengan jarak 15-20 cm<br>- Tunggu hingga kering</p>
A185: 120299 | B185: BLP Everyday - Kiss EDP | C185: 5d3ac307a6992471b7c97a2d | D185: 289000 | E185: 4.6666667e+15 | F185: <p>Show your true passion everyday and be bold with BLP EVERYDAY KISS <br><br>BLP EVERYDAY is a series of scents defined by the wearer – you! – to elevate your everyday ritual and speak volume of your confidence, elegance, freshness, and warmth. <br><br>Apply your favorite shade of red lipstick and walk to the room like you own it. A playful scent of bergamot and mandarin greets your passion. A dreamy pairing of muguet, gardenia, and jasmine makes you want to stay a little longer. With the warmth of cedarwood and tonka bean, remember that tonight is yours. <br><br>TOP <br>Bergamot, Mandarin, Aldehydes <br><br>HEART <br>Muguet, Gardenia, Jasmine <br><br>BASE <br>Cedarwood, Vanilla, Tonka Bean <br><br>SCENT CHARACTER <br>Bold | Floral | Feminine <br></p>
A186: 125300 | B186: Hello Prune - Nevernot Signature Series EDP | C186: 6979dfc48d450be00450df29 | D186: 189000 | E186: 5.0 | F186: <p>Parfum yang menghadirkan keinginan untuk rehat sejenak di alam, dengan aroma flowery yang fresh dan piknik-ready.</p> <p>NOTES<br>TOP: Magnolia, Bergamot<br>MIDDLE: Peach, Jasmine<br>BASE: Amber, Sandalwood, Vanilla </p> <p>Cocok buat kamu yang suka parfum fresh dan flowery!</p> <p>- Long-Lasting Scent, tahan hingga 6 jam<br>- Perfect for Daily Wear, wangi yang pas dan nyaman untuk aktivitas sehari-hari</p> <p>Cara Pakai<br>- Semprot pada titik nadi dengan jarak 15-20 cm<br>- Tunggu hingga kering</p>
A187: 122159 | B187: BARBIE Basilica Jasmine EDP | C187: 689c00257493d86323be7038 | D187: 299000 | E187: 5.0 | F187: <p>Parfum fruity floral yang memadukan aroma lychee, red rose, dan jasmine untuk kesan sweet, romantic, dan cheerful.</p> <p>NOTES<br>TOP: Lychee, Red Rose, Lollipop<br>MIDDLE: Raspberry, Jasmine, Heliotrope Flower<br>BASE: Musk, Rhubarb Leaf, Wood</p> <p>Cocok buat kamu yang suka parfum fruity floral dengan karakter manis, feminin, dan playful!</p> <p>- Long-Lasting Scent, tahan lama untuk menemani aktivitasmu<br>- Sweet Romantic Aroma, memberikan kesan ceria, manis, dan feminin<br>- Perfect for Daily Wear, nyaman dipakai untuk aktivitas harian maupun hangout</p> <p>Cara Pakai<br>- Semprotkan di urat nadi tangan, area leher belakang, dan belakang telinga<br>- Spray ke baju dengan jarak 15-20 cm</p>
A188: 124124 | B188: Jade Serenity Eau De Parfum | C188: 69292226555238423bb4eecf | D188: 295000 | E188: 4.6666667e+15 | F188: <p>Eau de parfum dengan oolong tea, violet leaf, dan floral notes yang bantu suasana terasa calm, mindful, dan empowered.</p> <p>Cocok buat kamu yang ingin wangi lembut untuk pause, reflect, dan reconnect dengan diri sendiri.</p> <p>- Mindfulness Scent, merelaksasi dan menciptakan calming atmosphere<br>- Dew-Covered Tea Field Inspiration, dengan sensasi fresh seperti tea fields<br>- Self-Reflection Mood, mendukung momen pause dan refleksi diri<br>- Empowering Feel, memberi kesan lebih clear dan empowered<br>- Consumer Tested, teruji berdasarkan satisfaction test pada 40 orang</p> <p>Fragrance Notes<br>- Top Notes: Bergamot, Violet Leaf, Peppermint Oil<br>- Middle Notes: Mimosa Absolute, Oolong Tea, Bulgarian Rose<br>- Base Notes: Sulawesi Patchouli, Cedarwood, Ambrostar</p> <p>Cara Pakai<br>- Semprotkan dari jarak 15–20 cm pada titik nadi</p>
A189: 125298 | B189: Petite Avenue - Nevernot Signature Series EDP | C189: 6979dfc48d450be00450df29 | D189: 189000 | E189: 46146 | F189: <p>Parfum yang menghadirkan vibes lobby hotel mewah dengan sentuhan floral dan jasmine tea yang elegan.</p> <p>NOTES<br>TOP: Earl Grey Tea, Mandarin Orange<br>MIDDLE: Freesia, Rose, Jasmine<br>BASE: Iris, Musk, Sandalwood </p> <p>Cocok buat kamu yang suka parfum calming dan floral!</p> <p>- Long-Lasting Scent, tahan hingga 6 jam<br>- Perfect for Daily Wear, wangi yang pas dan nyaman untuk aktivitas sehari-hari</p> <p>Cara Pakai<br>- Semprot pada titik nadi dengan jarak 15-20 cm<br>- Tunggu hingga kering</p>
A190: 125806 | B190: Project 1945 Fields of Ubud Perfume | Extrait de Parfum Unisex | C190: 64bf8ffd47133c15bf961d74 | D190: 345000 | E190: 5.0 | F190: <p>Terinspirasi dari indahnya Ubud, dimana lanskap anggun bernafas udara bersih bertemu budaya yang harmonis.<br><br><br><br>Fields of Ubud mengabadikan nuansa Ubud dengan padu padan Bergamot dan Elemi layaknya melangkahkan kaki pada hijaunya Teras Sawah Tegalalang nan asri sebagai wangi pembuka. <br><br>Dilanjutkan dengan wangi Lavender, Sea Salt &amp; Dried Fruit, seiring berjalan menyusuri otentiknya Pulau Dewata. <br><br>Sampai pada akhirnya wewangian earthy Vetiver Java, Sandalwood dan Oakmoss menjadi penutup lembut yang memikat.</p>
A191: 123380 | B191: Jacquelle x ZOOTOPIA Hair and Body Scent - Flirted Fox | C191: 5d3ac307a6992471b7c97bab | D191: 108000 | E191: 4.9333333e+15 | F191: <p><strong>Jacquelle Hair and Body Scent x ZOOTOPIA - Flirted Fox</strong><br>- Hair and Body Scent pertama di Indonesia<br>- Aroma Lychee segar menjadikan aroma yang manis, segar dalam satu waktu yang memancarkan kesan segar, energetic namun berkarakter yang memberikan kesan memikat yang cocok digunakan sehari-hari.<br>- Formula ramah untuk kulit dan rambut. Hair &amp; Body Scent ini khusus di formulasikan agar tidak membuat rambut kering dan kulit iritasi. Tidak meninggalkan kesan lengket di kulit. <br>- Koleksi Disney Limited Edition!<br>Hair &amp; Body Scent dikemas dengan packaging eksklusif dengan hasil kolaborasi dengan Disney yang wajib di koleksi bagi penggemar Disney.<br><br>Diformulasikan sebagai hair &amp; body scent pertama di Indonesia yang tidak hanya memberikan keharuman, tetapi juga menutrisi rambut dan kulit.<br>Diperkaya dengan castor oil untuk menjaga kelembapan tanpa rasa lengket, menjadikan rambut lembut dan kulit tetap halus sepanjang hari.<br>Wangi sweet fruity yang segar dan playful ini menggambarkan karakter Nick Wilde—charming, witty, dan penuh percaya diri. <br>Aroma yang ringan namun tahan lama, siap menemani setiap langkahmu dari siang hingga sore dengan penuh energi positif!</p>
A192: 122161 | B192: BARBIE Nord Rose EDP | C192: 689c00257493d86323be7038 | D192: 299000 | E192: 4.8461538e+15 | F192: <p>Parfum floral powdery yang menghadirkan aroma rose lembut, elegan, dan feminine dengan sentuhan chypre yang modern.</p> <p>NOTES<br>TOP: Rose Transparent Flower<br>MIDDLE: Iris Powder, Tuberose<br>BASE: Chypre Accord, Edible Notes</p> <p>Cocok buat kamu yang suka parfum floral powdery dengan karakter lembut, elegan, dan sophisticated!</p> <p>- Long-Lasting Scent, tahan lama untuk menemani aktivitasmu<br>- Elegant Floral Powdery Aroma, memberikan kesan feminin dan graceful<br>- Perfect for Daily &amp; Formal Wear, cocok dipakai untuk aktivitas harian hingga acara spesial</p> <p>Cara Pakai<br>- Semprotkan di urat nadi tangan, area leher belakang, dan belakang telinga<br>- Spray ke baju dengan jarak 15-20 cm</p>
A193: 123381 | B193: Jacquelle x ZOOTOPIA Hair and Body Scent - Midnight Blue | C193: 5d3ac307a6992471b7c97bab | D193: 108000 | E193: 4.3333333e+15 | F193: <p><strong>Jacquelle Hair and Body Scent x ZOOTOPIA - Midnight Blue</strong><br>- First Hair and Body Scent di Indonesia<br>-Kesan floral, clean, dan musky dalam satu waktu didapatkan dalam satu botol yang cocok digunakan sehari-hari bagi kamu yang aktif dan berdedikasi. <br>-Formula ramah untuk kulit dan rambut. Hair &amp; Body Scent ini khusus di formulasikan agar tidak membuat rambut kering dan kulit iritasi. Tidak meninggalkan kesan lengket di kulit. <br>-Koleksi Disney Limited Edition!<br>Hair &amp; Body Scent dikemas dengan packaging eksklusif dengan hasil kolaborasi dengan Disney yang wajib di koleksi bagi penggemar Disney.<br><br>Multifunction Hair &amp; Body Scent pertama di Indonesia yang bisa bikin kamu wangi sekaligus nourished dari ujung rambut sampai kulit!<br>Dengan castor oil yang bantu jaga kelembapan biar rambut gak kering dan kulit tetap halus, plus aroma sweet musky yang tahan lama—pas banget buat kamu yang aktif dan penuh semangat kayak Judy Hopps. <br>Fresh, clean, dan selalu siap nemenin kamu kejar mimpi siang malam!</p>
A194: 120987 | B194: Scent of Jarte Rose Petals Extrait de Parfum | C194: 5d3ac2ffa6992471b7c971d6 | D194: 285000 | E194: 4.7222222e+15 | F194: <p>Rose Petals terinspirasi dari mawar yang baru mekar di pagi hari, menghadirkan nuansa segar, tenang, dan effortless.</p><br /><p>NOTES<br>TOP: Bergamot, Mint, Lemon<br>MID: Turkish Rose, Hyacinth, Carnation<br>BASE: Musk, Heliotrope, Cedarwood</p> <p>Cocok buat kamu yang suka parfum floral, fresh flowers, dan musky dengan karakter light dan elegant!</p> <p>- Long-Lasting Scent, tahan lama untuk menemani aktivitasmu<br>- Perfect for Daily Wear, wangi yang pas dan nyaman untuk aktivitas sehari-hari</p> <p>Cara Pakai<br>- Semprot pada titik nadi dengan jarak 15-20 cm<br>- Tunggu hingga kering</p>
A195: 98257 | B195: Atlantis | C195: 6311def8368f94cfd772b44d | D195: 298000 | E195: 4.7311828e+15 | F195: <p>Atlantis menghadirkan aroma laut yang menyegarkan dan menawan, cocok untuk kamu yang ingin memberi kesan natural, fresh, dan luxury.</p> <p>NOTES<br>TOP: Grapefruit, Black Currant, Sea Salt<br>MID: Lily of the Valley, Pine, Jasmine<br>BASE: Amber, Praline</p> <p>Cocok buat kamu yang suka parfum fresh woody yang clean, aquatic, dan elegant!</p> <p>- Long-Lasting Scent, tahan lama untuk menemani aktivitasmu<br>- Perfect for Daily Wear, wangi yang pas dan nyaman untuk aktivitas sehari-hari</p> <p>Cara Pakai<br>- Semprot pada titik nadi dengan jarak 15-20 cm<br>- Tunggu hingga kering</p>
A196: 109664 | B196: Second Skin extrait de Parfume | C196: 658a8e243cca26bc8b2f676b | D196: 249000 | E196: 4.6814815e+15 | F196: <p>Second Skin dirancang untuk meniru aroma unik diri sendiri, membuat pemakainya merasa nyaman tanpa menutupi kepribadian aslinya.</p> <p>NOTES<br>TOP: Black Pepper, Bergamot, Clary Sage, Mandarin, Green Notes, Tagete<br>MID: Rose, Orange Flower, Violet, Lily of the Valley, Jasmine, Fruity Notes<br>BASE: Patchouli, Amber, Musk, Cedar, Lactone, Labdanum, Vanilla</p> <p>Cocok buat kamu yang suka parfum dengan karakter scent clean, warm, musky, comforting, natural, skin-like!</p> <p>- Long-Lasting Scent, tahan lama untuk menemani aktivitasmu<br>- Perfect for Daily Wear, wangi yang pas dan nyaman untuk aktivitas sehari-hari</p> <p>Cara Pakai<br>- Semprot pada titik nadi dengan jarak 15-20 cm<br>- Tunggu hingga kering</p>
A197: 119346 | B197: Santalscape Extrait de Parfum | C197: 657ad93e28f41e975c8a966c | D197: 350000 | E197: 4.5833333e+15 | F197: <p>Kahf Oracle Series Extrait de Parfum 50 ml merupakan New Series dari Kahf Fragrance yang membawakan inspirasi bagi pria untuk selalu menjadi pengingat tentang sosok yang mereka aspirasikan, dan nilai-nilai yang dibutuhkan untuk mencapai tujuan tersebut dengan menggabungkan Captive technology dan Essential oils untuk menciptakan fragrance yang bold, berbeda, aroma yang sangat baru, dan susah untuk ditiru.<br>TOP <br>Violet<br>Cardamom<br>MIDDLE<br>Ambertonic<br>Papyrus<br>Iris<br>Fig<br>BOTTOM<br>Sandalwood<br>Leather<br>Cedarwood<br>Operanide</p>
A198: 117781 | B198: Uptown | C198: 678f22b3bf9a94d16f30d103 | D198: 299000 | E198: 4.6666667e+15 | F198: <p>Parfum fresh fruity yang memancarkan positive vibes, cheerful energy, dan rasa percaya diri.</p> <p>NOTES<br>TOP: Strawberry, Black Currant, Red Apple, Citrus<br>MID: Sweat Pea, Fressia, Jasmine, Rose<br>BASE: Raspberry, Musk, Sandalwood, Amber</p> <p>Cocok buat kamu yang suka parfum fruity floral yang nyaman dipakai sepanjang hari!</p> <p>- Long-Lasting Scent, tahan lama untuk menemani aktivitasmu<br>- Fresh Fruity Floral Aroma, memberikan kesan ceria dan menarik<br>- Perfect for Daily Wear, nyaman dipakai untuk menemani aktivitas harian</p> <p>Cara Pakai<br>- Semprot pada titik nadi dengan jarak 15-20 cm<br>- Tunggu hingga kering</p>
A199: 124956 | B199: De Antoine Extrait De Parfume Opaque Ash | C199: 696f319a12cb95e5b7ae13b3 | D199: 280000 | E199: 3.6666667e+16 | F199: <p>Masuki dunia Opaque Ash, tempat elemen alam yang paling memikat berpadu dalam simfoni keanggunan yang refined. Wewangian ini dibuka dengan semburat segar grapefruit, manis berair pear, serta kehangatan rempah cardamom yang mengundang Anda ke dalam pelukan kemewahan. Pada bagian bagian, aroma berkembang dengan keindahan lembut rose dan lily of the valley, diperkaya oleh pesona dalam dan smoky dari tobacco leaves—sebuah sentuhan berani namun tetap anggun, menambah kompleksitas dan karakter sophisticated. Perjalanan aroma ini ditutup dengan base note yang kaya dan membumi dari patchouli, woody amber, cedarwood, serta manis hangat vanilla, meninggalkan jejak kemewahan yang abadi dan tak lekang oleh waktu. </p><p>Tobacco (Tembakau) &amp; Pear (Pir) (Sweet, Fresh - Manis,Segar)</p>
...

Sheet notes
A1: note_id | B1: note_name | C1: note_type
A2: 1 | B2: Cassis Buds | C2: top
A3: 2 | B3: Dalanghita | C3: top
A4: 3 | B4: Pink Pepper | C4: top
A5: 4 | B5: Duchesse de Nemours | C5: middle
A6: 5 | B6: Water Iris | C6: middle
A7: 6 | B7: Raat ki Rani | C7: middle
A8: 7 | B8: Warm Musky | C8: base
A9: 8 | C9: base
A10: 9 | C10: base
A11: 10 | B11: Mandarin | C11: top
A12: 11 | B12: Sweet Floral Notes | C12: middle
A13: 12 | B13: Vanilla Musk | C13: base
A14: 13 | B14: Sweet Mandarin | C14: top
A15: 14 | B15: Heliotrope | C15: middle
A16: 15 | B16: Creamy Gourmand | C16: base
A17: 16 | B17: Orange Blossom | C17: top
A18: 17 | B18: Pear | C18: top
A19: 18 | B19: Jasmine | C19: middle
A20: 19 | B20: Rose | C20: middle
A21: 20 | B21: Freesia | C21: middle
A22: 21 | B22: Bergamot | C22: top
... A388: 387 | B388: Bergamot | C388: middle
A389: 388 | C389: middle
A390: 389 | B390: rose | C390: middle
A391: 390 | B391: lily of the valley | C391: middle
A392: 391 | B392: Blond woods | C392: middle
A393: 392 | B393: jasmine | C393: middle
A394: 393 | B394: sandalwood creamy | C394: middle
A395: 394 | B395: white musk | C395: middle
A396: 395 | C396: middle
A397: 396 | B397: Rum | C397: top
A398: 397 | B398: Jasmine Sambac | C398: top
A399: 398 | B399: Mimosa dry | C399: middle
A400: 399 | B400: Sandal | C400: middle
A401: 400 | B401: Jasmine Sambac | C401: middle
A402: 401 | B402: Bunga putih | C402: middle
A403: 402 | B403: raspberry | C403: middle
A404: 403 | B404: Mimosa | C404: middle
A405: 404 | B405: Musk | C405: base
A406: 405 | B406: Wood | C406: base
A407: 406 | B407: Ambrette | C407: base
A408: 407 | B408: Nectarine Blossom | C408: top
... A420: 419 | B420: Blackberry Musk | C420: base
A421: 420 | C421: base
A422: 421 | B422: Ambrette | C422: base
A423: 422 | B423: Ambrette | C423: base
A424: 423 | B424: Red Cedar | C424: base
A425: 424 | B425: Red Cedar | C425: base
A426: 425 | B426: Ambrox | C426: base
A427: 426 | B427: Incense | C427: base
A428: 427 | B428: Incense | C428: base
A429: 428 | B429: Vetiver | C429: base
A430: 429 | B430: Blossom | C430: top
A431: 430 | B431: Lily of The Valley | C431: middle
A432: 431 | B432: Haitian Vetiver | C432: base
A433: 432 | B433: Musk | C433: base
A434: 433 | C434: base
A435: 434 | B435: WhiteMusk | C435: base
A436: 435 | B436: Warm Amber | C436: base
A437: 436 | B437: Lentisque | C437: base
A438: 437 | B438: Woods | C438: base
A439: 438 | B439: Woods | C439: base
A440: 439 | B440: Ambers | C440: base
A441: 440 | B441: Madagscar Vanilla | C441: base
A442: 441 | B442: Tonka Bean | C442: base
A443: 442 | B443: Ambergris | C443: base
A444: 443 | B444: Amber | C444: base
A445: 444 | B445: Ambergris | C445: base
A446: 445 | B446: Ambergris | C446: base
... A512: 511 | B512: vanilla | C512: middle
A513: 512 | C513: middle
A514: 513 | C514: middle
A515: 514 | C515: middle
A516: 515 | B516: Calone | C516: top
A517: 516 | B517: Rose Oxyd | C517: middle
A518: 517 | B518: Cedarwood | C518: middle
A519: 518 | B519: Ambroxan | C519: middle
A520: 519 | B520: Musk | C520: middle
A521: 520 | B521: airy | C521: middle
A522: 521 | B522: calone | C522: middle
A523: 522 | B523: cassis buds | C523: middle
A524: 523 | C524: middle
A525: 524 | B525: rose | C525: middle
A526: 525 | B526: cedarwood | C526: middle
A527: 526 | B527: ambroxan | C527: middle
A528: 527 | B528: musk | C528: middle
A529: 528 | B529: Sandalwood | C529: middle
A530: 529 | B530: Benzoin | C530: middle
A531: 530 | B531: Heliotropin | C531: middle
A532: 531 | B532: Coumarin | C532: middle
A533: 532 | B533: Orcanox | C533: middle
A534: 533 | B534: Lorenox | C534: middle
A535: 534 | B535: Dry Wood | C535: middle
A536: 535 | B536: Gourmand | C536: middle
... A662: 661 | B662: woods | C662: base
A663: 662 | C663: base
A664: 663 | B664: lasting softness. Fragrance notes : | C664: base
A665: 664 | B665: Litchi | C665: middle
A666: 665 | B666: Apple Blossom | C666: middle
...

Sheet productnotes
A1: product_id | B1: note_id | C1: note_type
A2: 117020 | B2: 1 | C2: top
A3: 117020 | B3: 2 | C3: top
A4: 117020 | B4: 3 | C4: top
A5: 117020 | B5: 4 | C5: middle
A6: 117020 | B6: 5 | C6: middle
A7: 117020 | B7: 6 | C7: middle
A8: 117020 | B8: 7 | C8: base
A9: 117020 | B9: 8 | C9: base
A10: 117020 | B10: 9 | C10: base
A11: 98385 | B11: 10 | C11: top
A12: 98385 | B12: 11 | C12: middle
A13: 98385 | B13: 12 | C13: base
... A2136: 109668 | B2136: 695 | C2136: middle

Sheet reviews
A1: review_id | B1: product_id | C1: review_text | D1: rating | E1: review_date
A2: 6a7aa572f3006db96997b841 | B2: 117020 | C2: Harumnya enak banget ,fresh dan cewek banget ,awet tahan lama di baju dan ninggalin jejak ,dipake panas-panasan pun harumnya tetap enak ,akan jadi parfum favorit ku dari saff n co ,dan akan repurchase lagi. | D2: 5 | E2: 2026-08-11T04:30:42.774Z
A3: 6a7e883857afb7c06ae37ad4 | B3: 117020 | C3: Wanginya seger semerbak bgttt! For daily used very suitable! Love this give you a very clean vibe kind of person. Longevity no need to ask. Saffnco always serve a very nice longevity | D3: 5 | E3: 2026-08-14T03:15:04.860Z
A4: 6a81772ad92cbca8c3f2dc25 | B4: 117020 | C4: terhidrasi dan halus. Wanginya juga cukup ringan sehingga masih nyaman digunakan. Untuk kulit yang sedang sensitif, mbahshbabajahahhababs dhshsbsbhsjsbsbs | D4: 5 | E4: 2026-08-16T08:39:06.646Z
A5: 69b9e3552c3442f15723ebe8 | B5: 117020 | C5: Kaka penjaga tokonya ramah, producknya bagus banget tahan lama, kebetulan dapat diskon jadi seneng banget bisa belanja di soviola, next pasti ke siciola lagi | D5: 5 | E5: 2026-03-17T23:27:17.706Z
A6: 69bb4dc4c1f7362b3a6a672c | B6: 117020 | C6: Parfume saff n co emang selalu unik-unik wanginyaaaa, sukaaa bangettt. Packagingnya jg mevvah sekaliii tp isi nya dikit cuma 35ml haha but wirth it karena di sociolla diskon 50% 🫶🏻✨ | D6: 5 | E6: 2026-03-19T01:13:40.832Z
A7: 69bb91cd62c7ea8e8a09290f | B7: 117020 | C7: Seger dna tahan lama banget di aku splmya dar der dor wanginya agak lean sedikit ke maskulin tapi masih unisex kok pokoknya selalu cinta sama saff n co | D7: 5 | E7: 2026-03-19T06:03:57.059Z
A8: 69bbd413e931b9db9c6f987f | B8: 117020 | C8: Sudah beli lagi yang ke 3 x harum nya enak sekali menurut aku. Seger banget dan tahan lama. Harga nya lumayan price karna saya beli ukuran yang kecil. | D8: 46207 | E8: 2026-03-19T10:46:43.715Z
A9: 69c1816b2ddbf3a9b27a4f0e | B9: 117020 | C9: udah repurchase parfum saff&co yg irai leima ini 3x karena wanginya seenak itu segerr kaya bau laut dan kalo dipake siang juga cocok ga bikin pusing atau mual | D9: 5 | E9: 2026-03-23T18:07:39.805Z
A10: 69c1cb498ef0e1e5621801b3 | B10: 117020 | C10: Wanginya enaakk seger bangett kek habis mandi dan temen2 kantorku & org rumah pada kepo aku pake parfum apa krn wanginya se nempel itu hahaha!! 😭✨👍🏻 dapet best deals bgtt kmaren jadi cuman 154k krn lagi diskon 50% + potongan point soco xixi 😍🤍 | D10: 5 | E10: 2026-03-23T23:22:49.847Z
A11: 69c2029ba4d3d5376d2ab7b9 | B11: 117020 | C11: Ini wangi ga bakal lo temuin di parfum mana pun sih!! Sniff pertama emang kaya wangi laut bersih, laut luar negeri, ada hint orange. Dry downnya wangi seger tapi elegan, dibilang wangi clean iya dibilang wangi sexy juga iya | D11: 5 | E11: 2026-03-24T03:18:51.437Z
A12: 69c2ac59b216f2b415ae4d9e | B12: 117020 | C12: Parfume ini baunya enak, lembut, kayak habis mandi, dia cocok ke semua hidung, seger. Parfumenya juga cocok dipakai disiang hari karena seger banget baunya | D12: 46207 | E12: 2026-03-24T15:23:05.587Z
A13: 69c51b8d9a18e97938caa613 | B13: 117020 | C13: beli ini blind buy, karna banyak lewat fyp yang review, wanginya ternyata beneran powdery soft enak banget, mau tes long lasting nya sih semoga tahan minimal di dalam ruangan yaa. so far goodd | D13: 5 | E13: 2026-03-26T11:42:05.633Z
... A30491: 6743e8f6e0e3c3bd98844c37 | B30491: 114801 | C30491: suka banget sama wanginya! super enak wangi rose nya soft bangeeeet, seger dan kalem aduh enak bgt. aku combo sama body mist nya yang love, rosy wah awet banget! | D30491: 5 | E30491: 2024-11-25T03:03:18.049Z
